james_files/RTL/mult_and_loader_v8_4x4/matrix.sv
`timescale 1 ns / 1 ps

module matrix(
    input CLK,
    input [255:0] flat_matrix_1,
    input [255:0] flat_matrix_2,
    input [3:0] R1,
    input [3:0] C1,
    input [3:0] R2,
    input [3:0] C2,
    input readybit,
    output reg [255:0] res_mat
);

    //parameter X_DIM = 2;
    //parameter Y_DIM = 2;
    //reg [31:0] x, y, z, i, j, k, index;

    wire [15:0] num0a, num1a, num2a, num3a, num4a, num5a, num6a, num7a, num8a, num9a, num10a, num11a, num12a, num13a, num14a, num15a;
    wire [15:0] num0b, num1b, num2b, num3b, num4b, num5b, num6b, num7b, num8b, num9b, num10b, num11b, num12b, num13b, num14b, num15b;

    wire [7:0] size;

    reg delay;

    // always @(readybit) begin
    //     $display("--- mult matrix ---");
    //     $display("[ %d %d %d ", num0a, num1a, num2a);
    //     $display(" %d %d %d ", num3a, num4a, num5a);
    //     $display(" %d %d %d ]", num6a, num7a, num8a);

    //     $display("--- mult matrix ---");
    //     $display("[ %d %d %d ", num0b, num1b, num2b);
    //     $display(" %d %d %d ", num3b, num4b, num5b);
    //     $display(" %d %d %d ]", num6b, num7b, num8b);
    // end

    always @(readybit) begin

        if(size == 4) begin
            //$display("size: ", R1," " ,C1);
            //$display("---------------------------------------------------------------");
            res_mat[63:48] <= num0a * num0b + num1a * num2b;
            res_mat[47:32] <= num0a * num1b + num1a * num3b;
            res_mat[31:16] <= num2a * num0b + num3a * num2b;
            res_mat[15:0]  <= num2a * num1b + num3a * num3b;
        end

        if(size == 9) begin
            //$display("size: ", R1," " ,C1);
            //$display("---------------------------------------------------------------");
            res_mat[143:128] <= num0a * num0b + num1a * num3b + num2a * num6b; // Row 1, Column 1
            res_mat[127:112] <= num0a * num1b + num1a * num4b + num2a * num7b; // Row 1, Column 2
            res_mat[111:96]  <= num0a * num2b + num1a * num5b + num2a * num8b; // Row 1, Column 3

            res_mat[95:80]   <= num3a * num0b + num4a * num3b + num5a * num6b; // Row 2, Column 1
            res_mat[79:64]   <= num3a * num1b + num4a * num4b + num5a * num7b; // Row 2, Column 2
            res_mat[63:48]   <= num3a * num2b + num4a * num5b + num5a * num8b; // Row 2, Column 3

            res_mat[47:32]   <= num6a * num0b + num7a * num3b + num8a * num6b; // Row 3, Column 1
            res_mat[31:16]   <= num6a * num1b + num7a * num4b + num8a * num7b; // Row 3, Column 2
            res_mat[15:0]    <= num6a * num2b + num7a * num5b + num8a * num8b; // Row 3, Column 3

        end

        if(size == 16) begin
            res_mat[255:240] <= num0a * num0b + num1a * num4b + num2a * num8b + num3a * num12b;
            res_mat[239:224] <= num0a * num1b + num1a * num5b + num2a * num9b + num3a * num13b;
            res_mat[223:208] <= num0a * num2b + num1a * num6b + num2a * num10b + num3a * num14b;
            res_mat[207:192] <= num0a * num3b + num1a * num7b + num2a * num11b + num3a * num15b;

            res_mat[191:176] <= num4a * num0b + num5a * num4b + num6a * num8b + num7a * num12b;
            res_mat[175:160] <= num4a * num1b + num5a * num5b + num6a * num9b + num7a * num13b;
            res_mat[159:144] <= num4a * num2b + num5a * num6b + num6a * num10b + num7a * num14b;
            res_mat[143:128] <= num4a * num3b + num5a * num7b + num6a * num11b + num7a * num15b;

            res_mat[127:112] <= num8a * num0b + num9a * num4b + num10a * num8b + num11a * num12b;
            res_mat[111:96]  <= num8a * num1b + num9a * num5b + num10a * num9b + num11a * num13b;
            res_mat[95:80]   <= num8a * num2b + num9a * num6b + num10a * num10b + num11a * num14b;
            res_mat[79:64]   <= num8a * num3b + num9a * num7b + num10a * num11b + num11a * num15b;

            res_mat[63:48]   <= num12a * num0b + num13a * num4b + num14a * num8b + num15a * num12b;
            res_mat[47:32]   <= num12a * num1b + num13a * num5b + num14a * num9b + num15a * num13b;
            res_mat[31:16]   <= num12a * num2b + num13a * num6b + num14a * num10b + num15a * num14b;
            res_mat[15:0]    <= num12a * num3b + num13a * num7b + num14a * num11b + num15a * num15b;
        end
    end

    assign num0a = flat_matrix_1[255:240];
    assign num1a = flat_matrix_1[239:224];
    assign num2a = flat_matrix_1[223:208];
    assign num3a = flat_matrix_1[207:192];

    assign num4a = flat_matrix_1[191:176];
    assign num5a = flat_matrix_1[175:160];
    assign num6a = flat_matrix_1[159:144];
    assign num7a = flat_matrix_1[143:128];
    assign num8a = flat_matrix_1[127:112];
    assign num9a = flat_matrix_1[111:96];

    assign num10a = flat_matrix_1[95:80];
    assign num11a = flat_matrix_1[79:64];
    assign num12a = flat_matrix_1[63:48];
    assign num13a = flat_matrix_1[47:32];
    assign num14a = flat_matrix_1[31:16];
    assign num15a = flat_matrix_1[15:0];


    assign num0b = flat_matrix_2[255:240];
    assign num1b = flat_matrix_2[239:224];
    assign num2b = flat_matrix_2[223:208];
    assign num3b = flat_matrix_2[207:192];
    assign num4b = flat_matrix_2[191:176];
    assign num5b = flat_matrix_2[175:160];
    assign num6b = flat_matrix_2[159:144];
    assign num7b = flat_matrix_2[143:128];
    assign num8b = flat_matrix_2[127:112];
    assign num9b = flat_matrix_2[111:96];
    assign num10b = flat_matrix_2[95:80];
    assign num11b = flat_matrix_2[79:64];
    assign num12b = flat_matrix_2[63:48];
    assign num13b = flat_matrix_2[47:32];
    assign num14b = flat_matrix_2[31:16];
    assign num15b = flat_matrix_2[15:0];

    assign size = R1*C1;

endmodule

james_files/RTL/mult_and_loader_v7_optimise/DflopX4.sv
`timescale 1 ns / 1 ps

module DflopX4(
    input wire CLK,
    input wire [7:0] a,
    output reg [7:0] x
    );

    always @(posedge CLK) begin
        x <= a;
    end

endmodule

james_files/RTL/mult_and_loader_v8_4x4/data_loader.sv
`timescale 1 ns / 1 ps

module data_loader(
    input wire CLK,
    input wire [7:0] data,
    input wire [1:0] ctrl_logic,
    output reg [255:0] res_mat
);
    reg [255:0] matrix_1;
    reg [255:0] matrix_2;

    reg [3:0] R1;
    reg [3:0] C1;

    reg [3:0] R2;
    reg [3:0] C2;

    reg [7:0] data_out;

    wire readybit;

    DflopX4 data_flop(CLK, data, data_out);
    matrix mult(CLK, matrix_1, matrix_2, R1, C1, R2, C2, readybit, res_mat);

    reg [1:0] count;
    reg [7:0] x, y;

    wire [4:0] y_max, x_max;

    initial begin
        count <= 0;
        x = 0;
        y = 0;
    end


    // always @* begin
    //     $display("Row 1: %d %d %d", matrix_1[255:240], matrix_1[239:224], matrix_1[223:208]);
    //     $display("Row 2: %d %d %d", matrix_1[207:192], matrix_1[191:176], matrix_1[175:160]);
    //     $display("Row 3: %d %d %d", matrix_1[159:144], matrix_1[143:128], matrix_1[127:112]);
    // end

    always @(posedge CLK) begin

        //$display( "R-C", R1, " ", C1, " ", R2, " ", C2 );

    // size of matrix
        if (ctrl_logic == 1) begin
            case(count)
                3'h0: R1 <= data_out;
                3'h1: C1 <= data_out;
                3'h2: R2 <= data_out;
                3'h3: C2 <= data_out;
            endcase
            count <= count + 1;
        end else if(ctrl_logic == 0) begin // matrix data

            if(x < x_max) begin
                //$display("x: ", x, "data_out: ", data_out);
                case(x)
                    8'd0: matrix_1[255:240] = data_out;
                    8'd1: matrix_1[239:224] = data_out;
                    8'd2: matrix_1[223:208] = data_out;
                    8'd3: matrix_1[207:192] = data_out;

                    8'd4: matrix_1[191:176] = data_out;
                    8'd5: matrix_1[175:160] = data_out;
                    8'd6: matrix_1[159:144] = data_out;
                    8'd7: matrix_1[143:128] = data_out;
                    8'd8: matrix_1[127:112] = data_out;

                    8'd9:  matrix_1[111:96] = data_out;
                    8'd10: matrix_1[95:80] = data_out;
                    8'd11: matrix_1[79:64] = data_out;
                    8'd12: matrix_1[63:48] = data_out;
                    8'd13: matrix_1[47:32] = data_out;
                    8'd14: matrix_1[31:16] = data_out;
                    8'd15: matrix_1[15:0] = data_out;
                endcase
                //$display("num5: ", matrix_1[143:128]);
                x = x + 1;
            end else if (y < y_max) begin 
                case(y)
                    8'd0: matrix_2[255:240] = data_out;
                    8'd1: matrix_2[239:224] = data_out;
                    8'd2: matrix_2[223:208] = data_out;
                    8'd3: matrix_2[207:192] = data_out;

                    8'd4: matrix_2[191:176] = data_out;
                    8'd5: matrix_2[175:160] = data_out;
                    8'd6: matrix_2[159:144] = data_out;
                    8'd7: matrix_2[143:128] = data_out;
                    8'd8: matrix_2[127:112] = data_out;

                    8'd9:  matrix_2[111:96] = data_out;
                    8'd10: matrix_2[95:80]  = data_out;
                    8'd11: matrix_2[79:64]  = data_out;
                    8'd12: matrix_2[63:48]  = data_out;
                    8'd13: matrix_2[47:32]  = data_out;
                    8'd14: matrix_2[31:16]  = data_out;
                    8'd15: matrix_2[15:0]   = data_out;
                endcase
                y = y + 1;
            end
        end else if (ctrl_logic == 2) begin
            x = 0;
            y = 0;
            count <= 0;
        end
    end

    assign x_max = R1*C1;
    assign y_max = R2*C2;
    assign readybit = (x == x_max && y == y_max) ? 1'b1 : 1'b0;
endmodule

//matrix_4x4[(15-x)*16 +: 16] = data_out;  // Dynamic bit slicing
//x = x + 1;  // Increment x to fill the next element

james_files/RTL/mult_and_loader_v8_4x4/advanced_tb.sv

// ----------------------
// Only need to change  MAT_XxX and NUM_MAT
// ----------------------

`timescale 1 ns / 1 ps

module advanced_tb();

    parameter MAT_XxX = 4; // x by x size; options, 2, 3, 4
    parameter NUM_MAT = 1; // set num of matrix to mult,

    parameter MAT_SIZE = 4; // dont change

    parameter CYCLE_LEN = (6 +  MAT_XxX*MAT_XxX * 2);

    reg CLK;
    reg [1:0] ctrl_logic;
    reg [7:0] data_send;
    
    reg [7:0] load_data [0:1270];
    reg [1:0] load_logic [0:2550];

    reg [255:0] res_mat;

    wire S0;

    integer data_i, logic_i, count; // matrix indexes
    integer i, j, k;                // for loop ints

    reg testo;

    data_loader loader(CLK, data_send, ctrl_logic, res_mat);

    initial begin
        
        $dumpfile("waveform.vcd"); // Specifies the name of the dump file
        $dumpvars(0, advanced_tb);   // Dumps all variables in the module "testbench" and its submodules
        CLK = 0;
        count = 0;
        logic_i = 0;
        data_i  = 0;

        ctrl_logic = 1;
        data_send = 2;

        // load data for NUM_MAT of MAT_SIZE * 2, (*2 for 2 matrix per mult)
        for(i = 0; i < NUM_MAT * MAT_XxX*MAT_XxX * 2; i++ ) begin
            load_data[i] = $random;
        end
        // load ctrl logic,
        for(i = 0; i < NUM_MAT*CYCLE_LEN; i++ ) begin

            load_logic[i] = 2;
            i = i + 1;
                
            for(j = 0; j < 4; j++) begin
                load_logic[i] = 1;
                i = i + 1;
            end
            for(j = 0; j < 2*MAT_XxX*MAT_XxX; j++) begin
                load_logic[i] = 0;
                i = i + 1;
            end
            load_logic[i] = 2;
        end

        // for(i = 0; i < MAT_XxX*MAT_XxX*2; i++)
        //     $display(i,": ", load_data[i]);
        // $display("---------------------------------------------------------");
        //  for(i = 0; i < NUM_MAT*14; i++)
        //      $display(load_logic[i]);

        forever #0.5 CLK = ~CLK;
    end

    //always #5 CLK=~CLK; //clock toggle every 0.5 ns

    always @(posedge CLK) begin

        ctrl_logic <= load_logic[logic_i++];

        if(count <= 3) begin
            data_send <= MAT_XxX;
        end else if((count > 3) && (count <= MAT_XxX*MAT_XxX*2+3)) begin
            data_send <= load_data[data_i];
            data_i = data_i + 1;
        end else if(count > MAT_XxX*MAT_XxX*2+3) begin
            data_send <= 0;
        end
        
        if(count == (CYCLE_LEN-1)) begin
            count = 0;
            #10
            if(MAT_XxX*MAT_XxX == 4) begin
                $display("--- result ---");
                $display(res_mat[63:48]," ", res_mat[47:32]);
                $display(res_mat[31:16]," ", res_mat[15:0]);
            end

            if(MAT_XxX*MAT_XxX == 9) begin
                $display("--- result ---");
                $display("%d %d %d", res_mat[143:128], res_mat[127:112], res_mat[111:96]);
                $display("%d %d %d", res_mat[95:80], res_mat[79:64], res_mat[63:48]);
                $display("%d %d %d", res_mat[47:32], res_mat[31:16], res_mat[15:0]);
            end

            if(MAT_XxX*MAT_XxX == 16) begin
                $display("--- result ---");
                $display("[ %d %d %d %d ]", res_mat[255:240], res_mat[239:224], res_mat[223:208], res_mat[207:192]);
                $display("[ %d %d %d %d ]", res_mat[191:176], res_mat[175:160], res_mat[159:144], res_mat[143:128]);
                $display("[ %d %d %d %d ]", res_mat[127:112], res_mat[111:96], res_mat[95:80], res_mat[79:64]);
                $display("[ %d %d %d %d ]", res_mat[63:48], res_mat[47:32], res_mat[31:16], res_mat[15:0]);
            end

        end else begin
            count = count + 1;
        end

        if(logic_i == CYCLE_LEN*NUM_MAT) begin
            #10
            $finish;
        end 
    end
endmodule

james_files/RTL/mult_and_loader_v8_4x4/waveform.vcd
$date
	Fri May 10 14:42:14 2024
$end
$version
	Icarus Verilog
$end
$timescale
	1ps
$end
$scope module advanced_tb $end
$var wire 256 ! res_mat [255:0] $end
$var parameter 97 " CYCLE_LEN $end
$var parameter 32 # MAT_SIZE $end
$var parameter 32 $ MAT_XxX $end
$var parameter 32 % NUM_MAT $end
$var reg 1 & CLK $end
$var reg 2 ' ctrl_logic [1:0] $end
$var reg 8 ( data_send [7:0] $end
$var integer 32 ) count [31:0] $end
$var integer 32 * data_i [31:0] $end
$var integer 32 + i [31:0] $end
$var integer 32 , j [31:0] $end
$var integer 32 - logic_i [31:0] $end
$scope module loader $end
$var wire 1 & CLK $end
$var wire 2 . ctrl_logic [1:0] $end
$var wire 8 / data [7:0] $end
$var wire 5 0 y_max [4:0] $end
$var wire 5 1 x_max [4:0] $end
$var wire 256 2 res_mat [255:0] $end
$var wire 1 3 readybit $end
$var wire 8 4 data_out [7:0] $end
$var reg 4 5 C1 [3:0] $end
$var reg 4 6 C2 [3:0] $end
$var reg 4 7 R1 [3:0] $end
$var reg 4 8 R2 [3:0] $end
$var reg 2 9 count [1:0] $end
$var reg 256 : matrix_1 [255:0] $end
$var reg 256 ; matrix_2 [255:0] $end
$var reg 8 < x [7:0] $end
$var reg 8 = y [7:0] $end
$scope module data_flop $end
$var wire 1 & CLK $end
$var wire 8 > a [7:0] $end
$var reg 8 ? x [7:0] $end
$upscope $end
$scope module mult $end
$var wire 4 @ C1 [3:0] $end
$var wire 4 A C2 [3:0] $end
$var wire 1 & CLK $end
$var wire 4 B R1 [3:0] $end
$var wire 4 C R2 [3:0] $end
$var wire 256 D flat_matrix_1 [255:0] $end
$var wire 256 E flat_matrix_2 [255:0] $end
$var wire 1 3 readybit $end
$var wire 8 F size [7:0] $end
$var wire 16 G num9b [15:0] $end
$var wire 16 H num9a [15:0] $end
$var wire 16 I num8b [15:0] $end
$var wire 16 J num8a [15:0] $end
$var wire 16 K num7b [15:0] $end
$var wire 16 L num7a [15:0] $end
$var wire 16 M num6b [15:0] $end
$var wire 16 N num6a [15:0] $end
$var wire 16 O num5b [15:0] $end
$var wire 16 P num5a [15:0] $end
$var wire 16 Q num4b [15:0] $end
$var wire 16 R num4a [15:0] $end
$var wire 16 S num3b [15:0] $end
$var wire 16 T num3a [15:0] $end
$var wire 16 U num2b [15:0] $end
$var wire 16 V num2a [15:0] $end
$var wire 16 W num1b [15:0] $end
$var wire 16 X num1a [15:0] $end
$var wire 16 Y num15b [15:0] $end
$var wire 16 Z num15a [15:0] $end
$var wire 16 [ num14b [15:0] $end
$var wire 16 \ num14a [15:0] $end
$var wire 16 ] num13b [15:0] $end
$var wire 16 ^ num13a [15:0] $end
$var wire 16 _ num12b [15:0] $end
$var wire 16 ` num12a [15:0] $end
$var wire 16 a num11b [15:0] $end
$var wire 16 b num11a [15:0] $end
$var wire 16 c num10b [15:0] $end
$var wire 16 d num10a [15:0] $end
$var wire 16 e num0b [15:0] $end
$var wire 16 f num0a [15:0] $end
$var reg 256 g res_mat [255:0] $end
$upscope $end
$upscope $end
$upscope $end
$enddefinitions $end
$comment Show the parameter values. $end
$dumpall
b1 %
b100 $
b100 #
b100110 "
$end
#0
$dumpvars
bx g
bx f
bx e
bx d
bx c
bx b
bx a
bx `
bx _
bx ^
bx ]
bx \
bx [
bx Z
bx Y
bx X
bx W
bx V
bx U
bx T
bx S
bx R
bx Q
bx P
bx O
bx N
bx M
bx L
bx K
bx J
bx I
bx H
bx G
bx F
bx E
bx D
bx C
bx B
bx A
bx @
bx ?
b10 >
b0 =
b0 <
bx ;
bx :
b0 9
bx 8
bx 7
bx 6
bx 5
bx 4
x3
bx 2
bx 1
bx 0
b10 /
b1 .
b0 -
b100000 ,
b100110 +
b0 *
b0 )
b10 (
b1 '
0&
bx !
$end
#500
b10 4
b10 ?
b1 9
b100 (
b100 /
b100 >
b10 '
b10 .
b1 )
b1 -
1&
#1000
0&
#1500
b1 '
b1 .
b0 9
b100 4
b100 ?
b10 )
b10 -
1&
#2000
0&
#2500
b1 9
b100 7
b100 B
b11 )
b11 -
1&
#3000
0&
#3500
03
b10 9
b10000 1
b10000 F
b100 5
b100 @
b100 )
b100 -
1&
#4000
0&
#4500
b11 9
b100 8
b100 C
b100100 (
b100100 /
b100100 >
b101 )
b1 *
b101 -
1&
#5000
0&
#5500
b10000001 (
b10000001 /
b10000001 >
b0 '
b0 .
b0 9
b10000 0
b100 6
b100 A
b100100 4
b100100 ?
b110 )
b10 *
b110 -
1&
#6000
0&
#6500
b10000001 4
b10000001 ?
b1001 (
b1001 /
b1001 >
b100100 f
b1 <
b100100xxxxxxxxxxxxxxxxxxxxxxxxxxxxxxxxxxxxxxxxxxxxxxxxxxxxxxxxxxxxxxxxxxxxxxxxxxxxxxxxxxxxxxxxxxxxxxxxxxxxxxxxxxxxxxxxxxxxxxxxxxxxxxxxxxxxxxxxxxxxxxxxxxxxxxxxxxxxxxxxxxxxxxxxxxxxxxxxxxxxxxxxxxxxxxxxxxxxxxxxxxxxxxxxxxxxxxxxxxxxxxxxxxxxxxxxxxxxxxxx :
b100100xxxxxxxxxxxxxxxxxxxxxxxxxxxxxxxxxxxxxxxxxxxxxxxxxxxxxxxxxxxxxxxxxxxxxxxxxxxxxxxxxxxxxxxxxxxxxxxxxxxxxxxxxxxxxxxxxxxxxxxxxxxxxxxxxxxxxxxxxxxxxxxxxxxxxxxxxxxxxxxxxxxxxxxxxxxxxxxxxxxxxxxxxxxxxxxxxxxxxxxxxxxxxxxxxxxxxxxxxxxxxxxxxxxxxxxxxxxxxxxx D
b111 )
b11 *
b111 -
1&
#7000
0&
#7500
b1100011 (
b1100011 /
b1100011 >
b1001 4
b1001 ?
b10000001 X
b1000 )
b100 *
b1000 -
b10 <
b1001000000000010000001xxxxxxxxxxxxxxxxxxxxxxxxxxxxxxxxxxxxxxxxxxxxxxxxxxxxxxxxxxxxxxxxxxxxxxxxxxxxxxxxxxxxxxxxxxxxxxxxxxxxxxxxxxxxxxxxxxxxxxxxxxxxxxxxxxxxxxxxxxxxxxxxxxxxxxxxxxxxxxxxxxxxxxxxxxxxxxxxxxxxxxxxxxxxxxxxxxxxxxxxxxxxxxxxxxxxxxxxxxxxxxxx :
b1001000000000010000001xxxxxxxxxxxxxxxxxxxxxxxxxxxxxxxxxxxxxxxxxxxxxxxxxxxxxxxxxxxxxxxxxxxxxxxxxxxxxxxxxxxxxxxxxxxxxxxxxxxxxxxxxxxxxxxxxxxxxxxxxxxxxxxxxxxxxxxxxxxxxxxxxxxxxxxxxxxxxxxxxxxxxxxxxxxxxxxxxxxxxxxxxxxxxxxxxxxxxxxxxxxxxxxxxxxxxxxxxxxxxxxx D
1&
#8000
0&
#8500
b1100011 4
b1100011 ?
b1101 (
b1101 /
b1101 >
b1001 V
b11 <
b10010000000000100000010000000000001001xxxxxxxxxxxxxxxxxxxxxxxxxxxxxxxxxxxxxxxxxxxxxxxxxxxxxxxxxxxxxxxxxxxxxxxxxxxxxxxxxxxxxxxxxxxxxxxxxxxxxxxxxxxxxxxxxxxxxxxxxxxxxxxxxxxxxxxxxxxxxxxxxxxxxxxxxxxxxxxxxxxxxxxxxxxxxxxxxxxxxxxxxxxxxxxxxxxxxxxxxxxxxxxx :
b10010000000000100000010000000000001001xxxxxxxxxxxxxxxxxxxxxxxxxxxxxxxxxxxxxxxxxxxxxxxxxxxxxxxxxxxxxxxxxxxxxxxxxxxxxxxxxxxxxxxxxxxxxxxxxxxxxxxxxxxxxxxxxxxxxxxxxxxxxxxxxxxxxxxxxxxxxxxxxxxxxxxxxxxxxxxxxxxxxxxxxxxxxxxxxxxxxxxxxxxxxxxxxxxxxxxxxxxxxxxx D
b1001 )
b101 *
b1001 -
1&
#9000
0&
#9500
b10001101 (
b10001101 /
b10001101 >
b1101 4
b1101 ?
b1100011 T
b1010 )
b110 *
b1010 -
b100 <
b100100000000001000000100000000000010010000000001100011xxxxxxxxxxxxxxxxxxxxxxxxxxxxxxxxxxxxxxxxxxxxxxxxxxxxxxxxxxxxxxxxxxxxxxxxxxxxxxxxxxxxxxxxxxxxxxxxxxxxxxxxxxxxxxxxxxxxxxxxxxxxxxxxxxxxxxxxxxxxxxxxxxxxxxxxxxxxxxxxxxxxxxxxxxxxxxxxxxxxxxxxxxxxxxxx :
b100100000000001000000100000000000010010000000001100011xxxxxxxxxxxxxxxxxxxxxxxxxxxxxxxxxxxxxxxxxxxxxxxxxxxxxxxxxxxxxxxxxxxxxxxxxxxxxxxxxxxxxxxxxxxxxxxxxxxxxxxxxxxxxxxxxxxxxxxxxxxxxxxxxxxxxxxxxxxxxxxxxxxxxxxxxxxxxxxxxxxxxxxxxxxxxxxxxxxxxxxxxxxxxxxx D
1&
#10000
0&
#10500
b10001101 4
b10001101 ?
b1100101 (
b1100101 /
b1100101 >
b1101 R
b101 <
b1001000000000010000001000000000000100100000000011000110000000000001101xxxxxxxxxxxxxxxxxxxxxxxxxxxxxxxxxxxxxxxxxxxxxxxxxxxxxxxxxxxxxxxxxxxxxxxxxxxxxxxxxxxxxxxxxxxxxxxxxxxxxxxxxxxxxxxxxxxxxxxxxxxxxxxxxxxxxxxxxxxxxxxxxxxxxxxxxxxxxxxxxxxxxxxxxxxxxxxx :
b1001000000000010000001000000000000100100000000011000110000000000001101xxxxxxxxxxxxxxxxxxxxxxxxxxxxxxxxxxxxxxxxxxxxxxxxxxxxxxxxxxxxxxxxxxxxxxxxxxxxxxxxxxxxxxxxxxxxxxxxxxxxxxxxxxxxxxxxxxxxxxxxxxxxxxxxxxxxxxxxxxxxxxxxxxxxxxxxxxxxxxxxxxxxxxxxxxxxxxxx D
b1011 )
b111 *
b1011 -
1&
#11000
0&
#11500
b10010 (
b10010 /
b10010 >
b1100101 4
b1100101 ?
b10001101 P
b1100 )
b1000 *
b1100 -
b110 <
b10010000000000100000010000000000001001000000000110001100000000000011010000000010001101xxxxxxxxxxxxxxxxxxxxxxxxxxxxxxxxxxxxxxxxxxxxxxxxxxxxxxxxxxxxxxxxxxxxxxxxxxxxxxxxxxxxxxxxxxxxxxxxxxxxxxxxxxxxxxxxxxxxxxxxxxxxxxxxxxxxxxxxxxxxxxxxxxxxxxxxxxxxxxxx :
b10010000000000100000010000000000001001000000000110001100000000000011010000000010001101xxxxxxxxxxxxxxxxxxxxxxxxxxxxxxxxxxxxxxxxxxxxxxxxxxxxxxxxxxxxxxxxxxxxxxxxxxxxxxxxxxxxxxxxxxxxxxxxxxxxxxxxxxxxxxxxxxxxxxxxxxxxxxxxxxxxxxxxxxxxxxxxxxxxxxxxxxxxxxxx D
1&
#12000
0&
#12500
b10010 4
b10010 ?
b1 (
b1 /
b1 >
b1100101 N
b111 <
b100100000000001000000100000000000010010000000001100011000000000000110100000000100011010000000001100101xxxxxxxxxxxxxxxxxxxxxxxxxxxxxxxxxxxxxxxxxxxxxxxxxxxxxxxxxxxxxxxxxxxxxxxxxxxxxxxxxxxxxxxxxxxxxxxxxxxxxxxxxxxxxxxxxxxxxxxxxxxxxxxxxxxxxxxxxxxxxxxx :
b100100000000001000000100000000000010010000000001100011000000000000110100000000100011010000000001100101xxxxxxxxxxxxxxxxxxxxxxxxxxxxxxxxxxxxxxxxxxxxxxxxxxxxxxxxxxxxxxxxxxxxxxxxxxxxxxxxxxxxxxxxxxxxxxxxxxxxxxxxxxxxxxxxxxxxxxxxxxxxxxxxxxxxxxxxxxxxxxxx D
b1101 )
b1001 *
b1101 -
1&
#13000
0&
#13500
b1101 (
b1101 /
b1101 >
b1 4
b1 ?
b10010 L
b1110 )
b1010 *
b1110 -
b1000 <
b1001000000000010000001000000000000100100000000011000110000000000001101000000001000110100000000011001010000000000010010xxxxxxxxxxxxxxxxxxxxxxxxxxxxxxxxxxxxxxxxxxxxxxxxxxxxxxxxxxxxxxxxxxxxxxxxxxxxxxxxxxxxxxxxxxxxxxxxxxxxxxxxxxxxxxxxxxxxxxxxxxxxxxxx :
b1001000000000010000001000000000000100100000000011000110000000000001101000000001000110100000000011001010000000000010010xxxxxxxxxxxxxxxxxxxxxxxxxxxxxxxxxxxxxxxxxxxxxxxxxxxxxxxxxxxxxxxxxxxxxxxxxxxxxxxxxxxxxxxxxxxxxxxxxxxxxxxxxxxxxxxxxxxxxxxxxxxxxxxx D
1&
#14000
0&
#14500
b1101 4
b1101 ?
b1110110 (
b1110110 /
b1110110 >
b1 J
b1001 <
b10010000000000100000010000000000001001000000000110001100000000000011010000000010001101000000000110010100000000000100100000000000000001xxxxxxxxxxxxxxxxxxxxxxxxxxxxxxxxxxxxxxxxxxxxxxxxxxxxxxxxxxxxxxxxxxxxxxxxxxxxxxxxxxxxxxxxxxxxxxxxxxxxxxxxxxxxxxxx :
b10010000000000100000010000000000001001000000000110001100000000000011010000000010001101000000000110010100000000000100100000000000000001xxxxxxxxxxxxxxxxxxxxxxxxxxxxxxxxxxxxxxxxxxxxxxxxxxxxxxxxxxxxxxxxxxxxxxxxxxxxxxxxxxxxxxxxxxxxxxxxxxxxxxxxxxxxxxxx D
b1111 )
b1011 *
b1111 -
1&
#15000
0&
#15500
b111101 (
b111101 /
b111101 >
b1110110 4
b1110110 ?
b1101 H
b10000 )
b1100 *
b10000 -
b1010 <
b100100000000001000000100000000000010010000000001100011000000000000110100000000100011010000000001100101000000000001001000000000000000010000000000001101xxxxxxxxxxxxxxxxxxxxxxxxxxxxxxxxxxxxxxxxxxxxxxxxxxxxxxxxxxxxxxxxxxxxxxxxxxxxxxxxxxxxxxxxxxxxxxxx :
b100100000000001000000100000000000010010000000001100011000000000000110100000000100011010000000001100101000000000001001000000000000000010000000000001101xxxxxxxxxxxxxxxxxxxxxxxxxxxxxxxxxxxxxxxxxxxxxxxxxxxxxxxxxxxxxxxxxxxxxxxxxxxxxxxxxxxxxxxxxxxxxxxx D
1&
#16000
0&
#16500
b111101 4
b111101 ?
b11101101 (
b11101101 /
b11101101 >
b1110110 d
b1011 <
b1001000000000010000001000000000000100100000000011000110000000000001101000000001000110100000000011001010000000000010010000000000000000100000000000011010000000001110110xxxxxxxxxxxxxxxxxxxxxxxxxxxxxxxxxxxxxxxxxxxxxxxxxxxxxxxxxxxxxxxxxxxxxxxxxxxxxxxx :
b1001000000000010000001000000000000100100000000011000110000000000001101000000001000110100000000011001010000000000010010000000000000000100000000000011010000000001110110xxxxxxxxxxxxxxxxxxxxxxxxxxxxxxxxxxxxxxxxxxxxxxxxxxxxxxxxxxxxxxxxxxxxxxxxxxxxxxxx D
b10001 )
b1101 *
b10001 -
1&
#17000
0&
#17500
b10001100 (
b10001100 /
b10001100 >
b11101101 4
b11101101 ?
b111101 b
b10010 )
b1110 *
b10010 -
b1100 <
b10010000000000100000010000000000001001000000000110001100000000000011010000000010001101000000000110010100000000000100100000000000000001000000000000110100000000011101100000000000111101xxxxxxxxxxxxxxxxxxxxxxxxxxxxxxxxxxxxxxxxxxxxxxxxxxxxxxxxxxxxxxxx :
b10010000000000100000010000000000001001000000000110001100000000000011010000000010001101000000000110010100000000000100100000000000000001000000000000110100000000011101100000000000111101xxxxxxxxxxxxxxxxxxxxxxxxxxxxxxxxxxxxxxxxxxxxxxxxxxxxxxxxxxxxxxxx D
1&
#18000
0&
#18500
b10001100 4
b10001100 ?
b11111001 (
b11111001 /
b11111001 >
b11101101 `
b1101 <
b100100000000001000000100000000000010010000000001100011000000000000110100000000100011010000000001100101000000000001001000000000000000010000000000001101000000000111011000000000001111010000000011101101xxxxxxxxxxxxxxxxxxxxxxxxxxxxxxxxxxxxxxxxxxxxxxxx :
b100100000000001000000100000000000010010000000001100011000000000000110100000000100011010000000001100101000000000001001000000000000000010000000000001101000000000111011000000000001111010000000011101101xxxxxxxxxxxxxxxxxxxxxxxxxxxxxxxxxxxxxxxxxxxxxxxx D
b10011 )
b1111 *
b10011 -
1&
#19000
0&
#19500
b11000110 (
b11000110 /
b11000110 >
b11111001 4
b11111001 ?
b10001100 ^
b10100 )
b10000 *
b10100 -
b1110 <
b1001000000000010000001000000000000100100000000011000110000000000001101000000001000110100000000011001010000000000010010000000000000000100000000000011010000000001110110000000000011110100000000111011010000000010001100xxxxxxxxxxxxxxxxxxxxxxxxxxxxxxxx :
b1001000000000010000001000000000000100100000000011000110000000000001101000000001000110100000000011001010000000000010010000000000000000100000000000011010000000001110110000000000011110100000000111011010000000010001100xxxxxxxxxxxxxxxxxxxxxxxxxxxxxxxx D
1&
#20000
0&
#20500
b11000110 4
b11000110 ?
b11000101 (
b11000101 /
b11000101 >
b11111001 \
b1111 <
b10010000000000100000010000000000001001000000000110001100000000000011010000000010001101000000000110010100000000000100100000000000000001000000000000110100000000011101100000000000111101000000001110110100000000100011000000000011111001xxxxxxxxxxxxxxxx :
b10010000000000100000010000000000001001000000000110001100000000000011010000000010001101000000000110010100000000000100100000000000000001000000000000110100000000011101100000000000111101000000001110110100000000100011000000000011111001xxxxxxxxxxxxxxxx D
b10101 )
b10001 *
b10101 -
1&
#21000
0&
