james_files/mult_and_loader/matrix.sv
module matrix(
    input wire CLK,
    input reg [31:0] flat_matrix_1 [0:4],
    input reg [31:0] flat_matrix_2 [0:4],
    input reg [3:0] R1,
    input reg [3:0] C1,
    input reg [3:0] R2,
    input reg [3:0] C2,
    input wire readybit

);

    parameter X_DIM = 2;
    parameter Y_DIM = 2;

    reg [127:0] matrix_1 [0:Y_DIM][0:X_DIM];
    reg [127:0] matrix_2 [0:Y_DIM][0:X_DIM];
    reg [127:0] rslt [0:Y_DIM][0:X_DIM];



    integer x, y, z;
    integer i, j, k;
    integer index;

    always @(posedge CLK) begin


        if(readybit) begin
            index = 0;
            for(i = 0; i < R1; i++) begin
                for(j = 0; j < C1; j++) begin
                    matrix_1[i][j] = flat_matrix_1[index++];
                end
            end

            index = 0;
            for(i = 0; i < R2; i++) begin
                for(j = 0; j < C2; j++) begin
                    matrix_2[i][j] = flat_matrix_2[index++];
                end
            end


            $display("matrix unflattened");
            $display(matrix_1[0][0], matrix_1[0][1]);
            $display(matrix_1[1][0], matrix_1[1][1]);
            $display("matrix unflattened");
            $display(matrix_2[0][0], matrix_2[0][1]);
            $display(matrix_2[1][0], matrix_2[1][1]);

            $display(" ---- Result ----");

            for (int i = 0; i < X_DIM; i++) begin
                for (int j = 0; j < Y_DIM; j++) begin
                    rslt[i][j] = 0;
        
                    for (int k = 0; k < X_DIM; k++) begin
                        rslt[i][j] += matrix_1[i][k] * matrix_2[k][j];
                    end
        
                    $write(rslt[i][j]);
                end
                $write("\n");
            end
                $finish;  //how long to run before stopping   
        end
    end

endmodule

james_files/vs1/data_loader_v3/DflopX4.sv
`timescale 1 ns / 1 ps

module DflopX4(
    input wire CLK,
    input wire [3:0] a,
    output reg [3:0] x
    );

    always @(posedge CLK) begin
        x <= a;
    end

endmodule

james_files/mult_and_loader/data_loader.sv
`timescale 1 ns / 1 ps

module loader(
    input wire CLK,
    input wire [3:0] data,
    input wire ctrl_logic
);

    parameter Y_DIM = 2;
    parameter X_DIM = 2;

    reg [31:0] matrix_1 [0:7];
    reg [31:0] matrix_2 [0:7];

    reg [3:0] R1;
    reg [3:0] C1;

    reg [3:0] R2;
    reg [3:0] C2;

    reg [3:0] data_out;

    reg testFlop;
    reg readybit;


    DflopX4 data_flop(CLK, data, data_out);
    matrix mult(CLK, matrix_1, matrix_2, R1, C1, R2, C2, readybit);

    integer count, x, y;

    initial begin
        count = 0;
        x = 0;
        y = 0;
        readybit = 0;
    end
    
    always @(posedge CLK) begin
        //$display(testFlop , "<=", data[0]);

       // $display("recieved ", data, " Flopped to ", data_out, " logic: ", ctrl_logic);

        // size of matrix
        if (ctrl_logic == 1) begin
            case(count)
                3'h1: R1 <= data_out;
                3'h2: C1 <= data_out;
                3'h3: R2 <= data_out;
                3'h4: C2 <= data_out;
            endcase
            count++;
        end else begin // matrix data
        if(x < C1*R1) begin
            matrix_1[x] = data_out;
            x = x + 1;
        end else if (y < C2*R2) begin 
            matrix_2[y] = data_out;
            y = y + 1;
        end

        if ((x==R1*C1) && (y==R2*C2))
            readybit = 1;
        end   
    end

endmodule

james_files/mult_and_loader/data_loader_tb.sv
`timescale 1 ns / 1 ps

module data_loader_tb();

    reg CLK, ctrl_logic;
    reg [3:0] data_send;
    integer count;
    wire S0;

    loader loader(CLK, data_send, ctrl_logic);
    initial begin

        $dumpfile("waveform.vcd"); // Specifies the name of the dump file
        $dumpvars(0, data_loader_tb);   // Dumps all variables in the module "testbench" and its submodules
        CLK = 0;
        count = 0;
        data_send = 2;
        ctrl_logic = 1;
        forever #0.5 CLK = ~CLK;
    end

    //always #5 CLK=~CLK; //clock toggle every 0.5 ns

    always @(posedge CLK) begin
        case(count)
            4'h0: begin
                data_send <= 2;
                ctrl_logic <= 1;
            end
            4'h1: begin
                data_send <= 2;
                ctrl_logic <= 1;
            end
            4'h2: begin
                data_send <= 2;
                ctrl_logic <= 1;
            end
            4'h3: begin
                data_send <= 8;
                ctrl_logic <= 1;
            end
            4'h4: begin
                data_send <= 1;
                ctrl_logic <= 0;
            end
            4'h5: begin
                data_send <= 15;
                ctrl_logic <= 0;
            end
            4'h6: begin
                data_send <= 2;
                ctrl_logic <= 0;
            end
            4'h7: begin
                data_send <= 2;
                ctrl_logic <= 0;
            end
            4'h8: begin
                data_send <= 1;
                ctrl_logic <= 0;
            end
            4'h9: begin
                data_send <= 9;
                ctrl_logic <= 0;
            end
            4'hA: begin
                data_send <= 2;
                ctrl_logic <= 0;
            end
            4'hB: begin
                $display("matrix loaded");
                $display(loader.matrix_1[0], loader.matrix_1[1]);
                $display(loader.matrix_1[2], loader.matrix_1[3]);
                $display("matrix loaded");
                $display(loader.matrix_2[0], loader.matrix_2[1]);
                $display(loader.matrix_2[2], loader.matrix_2[3]);
                $display("size");
                $display("R1: ", loader.R1, " C1: ", loader.C1);
                $display("R2: ", loader.R2, " C2: ", loader.C2);
                //$finish;
            end
        endcase
        count++;
    end


endmodule

james_files/mult_and_loader/waveform.vcd
$date
	Sun Apr 14 11:54:19 2024
$end
$version
	Icarus Verilog
$end
$timescale
	1ps
$end
$scope module data_loader_tb $end
$var reg 1 ! CLK $end
$var reg 1 " ctrl_logic $end
$var reg 4 # data_send [3:0] $end
$var integer 32 $ count [31:0] $end
$scope module loader $end
$var wire 1 ! CLK $end
$var wire 1 " ctrl_logic $end
$var wire 4 % data [3:0] $end
$var wire 4 & data_out [3:0] $end
$var parameter 32 ' X_DIM $end
$var parameter 32 ( Y_DIM $end
$var reg 4 ) C1 [3:0] $end
$var reg 4 * C2 [3:0] $end
$var reg 4 + R1 [3:0] $end
$var reg 4 , R2 [3:0] $end
$var reg 1 - readybit $end
$var integer 32 . count [31:0] $end
$var integer 32 / x [31:0] $end
$var integer 32 0 y [31:0] $end
$scope module data_flop $end
$var wire 1 ! CLK $end
$var wire 4 1 a [3:0] $end
$var reg 4 2 x [3:0] $end
$upscope $end
$scope module mult $end
$var wire 4 3 C1 [3:0] $end
$var wire 4 4 C2 [3:0] $end
$var wire 1 ! CLK $end
$var wire 4 5 R1 [3:0] $end
$var wire 4 6 R2 [3:0] $end
$var wire 1 - readybit $end
$var parameter 32 7 X_DIM $end
$var parameter 32 8 Y_DIM $end
$var integer 32 9 i [31:0] $end
$var integer 32 : index [31:0] $end
$var integer 32 ; j [31:0] $end
$scope begin $ivl_for_loop0 $end
$var integer 32 < i [31:0] $end
$scope begin $ivl_for_loop1 $end
$var integer 32 = j [31:0] $end
$scope begin $ivl_for_loop2 $end
$var integer 32 > k [31:0] $end
$upscope $end
$upscope $end
$upscope $end
$upscope $end
$upscope $end
$upscope $end
$enddefinitions $end
$comment Show the parameter values. $end
$dumpall
b10 8
b10 7
b10 (
b10 '
$end
#0
$dumpvars
b0 >
b0 =
b0 <
bx ;
bx :
bx 9
bx 6
bx 5
bx 4
bx 3
bx 2
b10 1
b0 0
b0 /
b0 .
0-
bx ,
bx +
bx *
bx )
bx &
b10 %
b0 $
b10 #
1"
0!
$end
#500
b10 &
b10 2
b1 .
b1 $
1!
#1000
0!
#1500
b10 +
b10 5
b10 $
b10 .
1!
#2000
0!
#2500
b10 )
b10 3
b11 .
b11 $
1!
#3000
0!
#3500
b1000 #
b1000 %
b1000 1
b10 ,
b10 6
b100 $
b100 .
1!
#4000
0!
#4500
b1000 &
b1000 2
b10 *
b10 4
0"
b1 #
b1 %
b1 1
b101 .
b101 $
1!
#5000
0!
#5500
b1111 #
b1111 %
b1111 1
b1 &
b1 2
b110 $
b1 /
1!
#6000
0!
#6500
b1111 &
b1111 2
b10 #
b10 %
b10 1
b10 /
b111 $
1!
#7000
0!
#7500
b10 &
b10 2
b1000 $
b11 /
1!
#8000
0!
#8500
b1 #
b1 %
b1 1
b100 /
b1001 $
1!
#9000
0!
#9500
b1001 #
b1001 %
b1001 1
b1 &
b1 2
b1010 $
b1 0
1!
#10000
0!
#10500
b1001 &
b1001 2
b10 #
b10 %
b10 1
b10 0
b1011 $
1!
#11000
0!
#11500
b10 &
b10 2
b1100 $
b11 0
1!
#12000
0!
#12500
b10 <
b10 =
b10 >
b10 ;
b10 9
b100 :
1-
b100 0
b1101 $
1!
