james_files/RTL/mult_and_loader_v3 - Copy/matrix.sv
`timescale 1 ns / 1 ps

module matrix(
    input wire CLK,
    input wire [31:0] flat_matrix_1 [0:3], // need to get rid of the 2-d matrix
    input wire [31:0] flat_matrix_2 [0:3],
    input wire [3:0] R1,
    input wire [3:0] C1,
    input wire [3:0] R2,
    input wire [3:0] C2,
    input wire readybit,
    output reg startbit
);

    parameter X_DIM = 2;
    parameter Y_DIM = 2;

    reg [127:0] matrix_1 [0:Y_DIM][0:X_DIM];
    reg [127:0] matrix_2 [0:Y_DIM][0:X_DIM];
    reg [127:0] rslt [0:Y_DIM][0:X_DIM];

    integer x, y, z;
    integer i, j, k, rb;
    integer index;

    reg delay;

    always @(posedge CLK) begin
        startbit = 0;


        if(readybit) begin
            startbit = 1;
            #2
            //$display("started: ", $realtime, " ", readybit);
            index = 0;
            for(i = 0; i < R1; i++) begin
                for(j = 0; j < C1; j++) begin
                    matrix_1[i][j] = flat_matrix_1[index++];
                end
            end

            index = 0;
            for(i = 0; i < R2; i++) begin
                for(j = 0; j < C2; j++) begin
                    matrix_2[i][j] = flat_matrix_2[index++];
                end
            end

            $display("matrix unflattened");
            $display(matrix_1[0][0], matrix_1[0][1]);
            $display(matrix_1[1][0], matrix_1[1][1]);
            $display("matrix unflattened");
            $display(matrix_2[0][0], matrix_2[0][1]);
            $display(matrix_2[1][0], matrix_2[1][1]);

            $display(" ---- Result ----");

            for (int i = 0; i < X_DIM; i++) begin
                for (int j = 0; j < Y_DIM; j++) begin
                    rslt[i][j] = 0;
        
                    for (int k = 0; k < X_DIM; k++) begin
                        rslt[i][j] += matrix_1[i][k] * matrix_2[k][j];
                    end
        
                    $write(rslt[i][j]);
                end
                $write("\n");
            end
        end
    end

endmodule

james_files/RTL/mult_and_loader_v7_optimise/DflopX4.sv
`timescale 1 ns / 1 ps

module DflopX4(
    input wire CLK,
    input wire [7:0] a,
    output reg [7:0] x
    );

    always @(posedge CLK) begin
        x <= a;
    end

endmodule

james_files/RTL/mult_and_loader_v3 - Copy/data_loader.sv
`timescale 1 ns / 1 ps

module loader(
    input wire CLK,
    input wire [7:0] data,
    input wire [1:0] ctrl_logic
);

    parameter Y_DIM = 2;
    parameter X_DIM = 2;

    reg [31:0] matrix_1 [0:3];
    reg [31:0] matrix_2 [0:3];

    reg [3:0] R1;
    reg [3:0] C1;

    reg [3:0] R2;
    reg [3:0] C2;

    reg [7:0] data_out;

    reg testFlop;
    reg readybit;
    reg startbit;

    reg skip;


    DflopX4 data_flop(CLK, data, data_out);
    matrix mult(CLK, matrix_1, matrix_2, R1, C1, R2, C2, readybit, startbit);

    integer count, x, y, testclock;

    initial begin
        count = 0;
        x = 0;
        y = 0;
        readybit = 0;
        testclock = -1;

        skip = 1;
    end

    always @(posedge startbit) begin
        readybit = 0;
    end
    
    always @(posedge CLK) begin
       // if(skip != 1) begin
    //$display("data: ", data_out, " logic: ", ctrl_logic);

    // size of matrix
        if (ctrl_logic == 1) begin
            //$display("count: ",count, " data: ", data_out);
            case(count)
                3'h0: R1 <= data_out;
                3'h1: C1 <= data_out;
                3'h2: R2 <= data_out;
                3'h3: C2 <= data_out;
            endcase
            count++;
        end else if(ctrl_logic == 0) begin // matrix data
            if(x < C1*R1) begin
                matrix_1[x] = data_out;
                x = x + 1;
            end else if (y < C2*R2) begin 
                
                matrix_2[y] = data_out;
                y = y + 1;
            end

            //$display("ckock: ", testclock, " t/f: ", (x==R1*C1) && (y==R2*C2), " logic: ", ctrl_logic, " xy: ", x,y);
            if ((x==R1*C1) && (y==R2*C2))
                //$display("mult now");
                readybit = 1;
        end else if (ctrl_logic == 2) begin
            
            //$display("here");
            readybit <= 0;
            x <= 0;
            y <= 0;
            count <= 0;
        end
       // end
        skip = 0;
    end

endmodule

james_files/RTL/mult_and_loader_v3/advanced_tb.sv
`timescale 1 ns / 1 ps

module data_loader_tb();

    parameter NUM_MAT = 3; // set num of matrix to mult
    parameter MAT_SIZE = 4; // set num of matrix to mult
    parameter MAT_XxX = 2; // x by x size


    reg CLK;
    reg [1:0] ctrl_logic;
    reg [7:0] data_send;
    
    reg [7:0] load_data [0:127];
    reg [1:0] load_logic [0:255];

    wire S0;

    integer data_i, logic_i, count; // matrix indexes
    integer i, j, k;                // for loop ints

    loader loader(CLK, data_send, ctrl_logic);

    initial begin
        

        $dumpfile("waveform.vcd"); // Specifies the name of the dump file
        $dumpvars(0, data_loader_tb);   // Dumps all variables in the module "testbench" and its submodules
        CLK = 0;
        count = 1;
        logic_i = 0;
        data_i  = 0;

        ctrl_logic = 1;
        data_send = 2;

        // load data for NUM_MAT of MAT_SIZE * 2, (*2 for 2 matrix per mult)
        for(i = 0; i < NUM_MAT * MAT_SIZE * 2; i++ ) begin
            load_data[i] = $random;
        end

        // load ctrl logic,
        for(i = 0; i < NUM_MAT*14; i++ ) begin

            if(i != 0)
                load_logic[i++] = 2;
                
            for(j = 0; j < 4; j++)
                load_logic[i++] = 1;
            for(j = 0; j < 2*MAT_SIZE; j++)
                load_logic[i++] = 0;
            load_logic[i] = 2;
        end

        // for(i = 0; i < NUM_MAT*8; i++)
        //     $display(load_data[i]);
        // $display("---------------------------------------------------------");
        //  for(i = 0; i < NUM_MAT*14; i++)
        //      $display(load_logic[i]);

        forever #0.5 CLK = ~CLK;
    end

    //always #5 CLK=~CLK; //clock toggle every 0.5 ns

    always @(posedge CLK) begin

            // $display("size");
            // $display("R1: ", loader.R1, " C1: ", loader.C1);
            // $display("R2: ", loader.R2, " C2: ", loader.C2);

        //$display("logic: ", logic_i);
        ctrl_logic <= load_logic[logic_i++];
        case(count)
            8'h0:
                data_send <= MAT_XxX;
            8'h1:
                data_send <= MAT_XxX;
            8'h2:
                data_send <= MAT_XxX;
            8'h3: 
                data_send <= MAT_XxX;
            8'h4: 
                data_send <= load_data[data_i++];
            8'h5: 
                data_send <= load_data[data_i++];
            8'h6: 
                data_send <= load_data[data_i++];
            8'h7: 
                data_send <= load_data[data_i++];
            8'h8: 
                data_send <= load_data[data_i++];
            8'h9:
                data_send <= load_data[data_i++];
            8'hA: 
                data_send <= load_data[data_i++];
            8'hB:
                data_send <= load_data[data_i++];
            8'hC:
                data_send <= 0;
            8'hD:
                data_send <= 0;
        endcase
        
        // || (logic_i == 14 & count == 14)
        if(count == 13) begin
            count = 0;
        end else begin
            count = count + 1;
        end

        if(logic_i == 14*NUM_MAT) begin
            #5
            $finish;
        end 
    end
endmodule



// $display("matrix loaded");
// $display(loader.matrix_1[0], loader.matrix_1[1]);
// $display(loader.matrix_1[2], loader.matrix_1[3]);
// $display("matrix loaded");
// $display(loader.matrix_2[0], loader.matrix_2[1]);
// $display(loader.matrix_2[2], loader.matrix_2[3]);
// $display("size");
// $display("R1: ", loader.R1, " C1: ", loader.C1);
// $display("R2: ", loader.R2, " C2: ", loader.C2);

//    case(count)
//             4'h0: begin
//                 data_send <= MAT_XxX;
//                 ctrl_logic <= ;
//             end
//             4'h1: begin
//                 data_send <= 2;
//                 ctrl_logic <= 1;
//             end
//             4'h2: begin
//                 data_send <= 2;
//                 ctrl_logic <= 1;
//             end
//             4'h3: begin
//                 data_send <= 8;
//                 ctrl_logic <= 1;
//             end
//             4'h4: begin
//                 data_send <= 1;
//                 ctrl_logic <= 0;
//             end
//             4'h5: begin
//                 data_send <= 15;
//                 ctrl_logic <= 0; 
//             end
//             4'h6: begin
//                 data_send <= 2;
//                 ctrl_logic <= 0; 
//             end
//             4'h7: begin
//                 data_send <= 2;
//                 ctrl_logic <= 0;
//             end
//             4'h8: begin
//                 data_send <= 1;
//                 ctrl_logic <= 0;
//             end
//             4'h9: begin
//                 data_send <= 9;
//                 ctrl_logic <= 0;
//             end
//             4'hA: begin
//                 data_send <= 2;
//                 ctrl_logic <= 0;
//             end
//             4'hB: begin
//                 data_send <= x;
//                 ctrl_logic <= 0;
//             end
//             8'hC: begin
//                 data_send <= 2;
//                 ctrl_logic <= 2;
//             end
//             8'hD: begin
//                 data_send <= 2;
//                 ctrl_logic <= 1;
//             end
//         endcase

james_files/RTL/mult_and_loader_v3/waveform.vcd
$date
	Tue Apr 23 08:16:48 2024
$end
$version
	Icarus Verilog
$end
$timescale
	1ps
$end
$scope module data_loader_tb $end
$var parameter 32 ! MAT_SIZE $end
$var parameter 32 " MAT_XxX $end
$var parameter 32 # NUM_MAT $end
$var reg 1 $ CLK $end
$var reg 2 % ctrl_logic [1:0] $end
$var reg 8 & data_send [7:0] $end
$var integer 32 ' count [31:0] $end
$var integer 32 ( data_i [31:0] $end
$var integer 32 ) i [31:0] $end
$var integer 32 * j [31:0] $end
$var integer 32 + logic_i [31:0] $end
$scope module loader $end
$var wire 1 $ CLK $end
$var wire 2 , ctrl_logic [1:0] $end
$var wire 8 - data [7:0] $end
$var wire 1 . startbit $end
$var wire 8 / data_out [7:0] $end
$var parameter 32 0 X_DIM $end
$var parameter 32 1 Y_DIM $end
$var reg 4 2 C1 [3:0] $end
$var reg 4 3 C2 [3:0] $end
$var reg 4 4 R1 [3:0] $end
$var reg 4 5 R2 [3:0] $end
$var reg 1 6 readybit $end
$var reg 1 7 skip $end
$var integer 32 8 count [31:0] $end
$var integer 32 9 testclock [31:0] $end
$var integer 32 : x [31:0] $end
$var integer 32 ; y [31:0] $end
$scope module data_flop $end
$var wire 1 $ CLK $end
$var wire 8 < a [7:0] $end
$var reg 8 = x [7:0] $end
$upscope $end
$scope module mult $end
$var wire 4 > C1 [3:0] $end
$var wire 4 ? C2 [3:0] $end
$var wire 1 $ CLK $end
$var wire 4 @ R1 [3:0] $end
$var wire 4 A R2 [3:0] $end
$var wire 1 6 readybit $end
$var parameter 32 B X_DIM $end
$var parameter 32 C Y_DIM $end
$var reg 1 . startbit $end
$var integer 32 D i [31:0] $end
$var integer 32 E index [31:0] $end
$var integer 32 F j [31:0] $end
$scope begin $ivl_for_loop0 $end
$var integer 32 G i [31:0] $end
$scope begin $ivl_for_loop1 $end
$var integer 32 H j [31:0] $end
$scope begin $ivl_for_loop2 $end
$var integer 32 I k [31:0] $end
$upscope $end
$upscope $end
$upscope $end
$upscope $end
$upscope $end
$upscope $end
$enddefinitions $end
$comment Show the parameter values. $end
$dumpall
b10 C
b10 B
b10 1
b10 0
b11 #
b10 "
b100 !
$end
#0
$dumpvars
b0 I
b0 H
b0 G
bx F
bx E
bx D
bx A
bx @
bx ?
bx >
bx =
b10 <
b0 ;
b0 :
b11111111111111111111111111111111 9
b0 8
17
06
bx 5
bx 4
bx 3
bx 2
bx /
x.
b10 -
b1 ,
b0 +
b1000 *
b110111 )
b0 (
b1 '
b10 &
b1 %
0$
$end
#500
b10 /
b10 =
0.
07
b1 8
b10 '
b1 +
1$
#1000
0$
#1500
b10 4
b10 @
b11 '
b10 +
b10 8
1$
#2000
0$
#2500
b10 2
b10 >
b11 8
b100 '
b11 +
1$
#3000
0$
#3500
b100100 &
b100100 -
b100100 <
b10 5
b10 A
b101 '
b1 (
b100 +
b100 8
1$
#4000
0$
#4500
b100100 /
b100100 =
b10 3
b10 ?
b10000001 &
b10000001 -
b10000001 <
b0 %
b0 ,
b101 8
b110 '
b10 (
b101 +
1$
#5000
0$
#5500
b1001 &
b1001 -
b1001 <
b10000001 /
b10000001 =
b111 '
b11 (
b110 +
b1 :
1$
#6000
0$
#6500
b1001 /
b1001 =
b1100011 &
b1100011 -
b1100011 <
b10 :
b1000 '
b100 (
b111 +
1$
#7000
0$
#7500
b1101 &
b1101 -
b1101 <
b1100011 /
b1100011 =
b1001 '
b101 (
b1000 +
b11 :
1$
#8000
0$
#8500
b1101 /
b1101 =
b10001101 &
b10001101 -
b10001101 <
b100 :
b1010 '
b110 (
b1001 +
1$
#9000
0$
#9500
b1100101 &
b1100101 -
b1100101 <
b10001101 /
b10001101 =
b1011 '
b111 (
b1010 +
b1 ;
1$
#10000
0$
#10500
b1100101 /
b1100101 =
b10010 &
b10010 -
b10010 <
b10 ;
b1100 '
b1000 (
b1011 +
1$
#11000
0$
#11500
b0 &
b0 -
b0 <
b10010 /
b10010 =
b1101 '
b1100 +
b11 ;
1$
#12000
0$
#12500
b0 /
b0 =
b10 %
b10 ,
1.
06
b100 ;
b0 '
b1101 +
1$
#13000
0$
#13500
b10 &
b10 -
b10 <
b0 8
b0 ;
b0 :
b1 '
b1110 +
1$
#14000
0$
#14500
b10 /
b10 =
b1 %
b1 ,
b10 '
b1111 +
0.
1$
b10 G
b10 H
b10 I
b10 F
b10 D
b100 E
#15000
0$
#15500
b11 '
b10000 +
b1 8
1$
#16000
0$
#16500
b10 8
b100 '
b10001 +
1$
#17000
0$
#17500
b1 &
b1 -
b1 <
b101 '
b1001 (
b10010 +
b11 8
1$
#18000
0$
#18500
b1 /
b1 =
b1101 &
b1101 -
b1101 <
b0 %
b0 ,
b100 8
b110 '
b1010 (
b10011 +
1$
#19000
0$
#19500
b1110110 &
b1110110 -
b1110110 <
b1101 /
b1101 =
b111 '
b1011 (
b10100 +
b1 :
1$
#20000
0$
#20500
b1110110 /
b1110110 =
b111101 &
b111101 -
b111101 <
b10 :
b1000 '
b1100 (
b10101 +
1$
#21000
0$
#21500
b11101101 &
b11101101 -
b11101101 <
b111101 /
b111101 =
b1001 '
b1101 (
b10110 +
b11 :
1$
#22000
0$
#22500
b11101101 /
b11101101 =
b10001100 &
b10001100 -
b10001100 <
b100 :
b1010 '
b1110 (
b10111 +
1$
#23000
0$
#23500
b11111001 &
b11111001 -
b11111001 <
b10001100 /
b10001100 =
b1011 '
b1111 (
b11000 +
b1 ;
1$
#24000
0$
#24500
b11111001 /
b11111001 =
b11000110 &
b11000110 -
b11000110 <
b10 ;
b1100 '
b10000 (
b11001 +
1$
#25000
0$
#25500
b0 &
b0 -
b0 <
b11000110 /
b11000110 =
b1101 '
b11010 +
b11 ;
1$
#26000
0$
#26500
b0 /
b0 =
b10 %
b10 ,
16
b100 ;
b0 '
b11011 +
1$
#27000
0$
#27500
b10 &
b10 -
b10 <
b0 8
b0 ;
b0 :
06
1.
b1 '
b11100 +
1$
#28000
0$
#28500
b10 /
b10 =
b1 %
b1 ,
b10 '
b11101 +
1$
#29000
0$
#29500
b11 '
b11110 +
b1 8
0.
1$
b10 I
b10 H
b10 G
b10 F
b10 D
b100 E
#30000
0$
#30500
b10 8
b100 '
b11111 +
1$
#31000
0$
#31500
b11000101 &
b11000101 -
b11000101 <
b101 '
b10001 (
b100000 +
b11 8
1$
#32000
0$
#32500
b11000101 /
b11000101 =
b10101010 &
b10101010 -
b10101010 <
b0 %
b0 ,
b100 8
b110 '
b10010 (
b100001 +
1$
#33000
0$
#33500
b11100101 &
b11100101 -
b11100101 <
b10101010 /
b10101010 =
b111 '
b10011 (
b100010 +
b1 :
1$
#34000
0$
#34500
b11100101 /
b11100101 =
b1110111 &
b1110111 -
b1110111 <
b10 :
b1000 '
b10100 (
b100011 +
1$
#35000
0$
#35500
b10010 &
b10010 -
b10010 <
b1110111 /
b1110111 =
b1001 '
b10101 (
b100100 +
b11 :
1$
#36000
0$
#36500
b10010 /
b10010 =
b10001111 &
b10001111 -
b10001111 <
b100 :
b1010 '
b10110 (
b100101 +
1$
#37000
0$
#37500
b11110010 &
b11110010 -
b11110010 <
b10001111 /
b10001111 =
b1011 '
b10111 (
b100110 +
b1 ;
1$
#38000
0$
#38500
b11110010 /
b11110010 =
b11001110 &
b11001110 -
b11001110 <
b10 ;
b1100 '
b11000 (
b100111 +
1$
#39000
0$
#39500
b0 &
b0 -
b0 <
b11001110 /
b11001110 =
b1101 '
b101000 +
b11 ;
1$
#40000
0$
#40500
b0 /
b0 =
b10 %
b10 ,
1.
06
b100 ;
b0 '
b101001 +
1$
#41000
0$
#41500
b10 &
b10 -
b10 <
b0 8
b0 ;
b0 :
b1 '
b101010 +
1$
#42000
0$
#42500
b10 /
b10 =
0.
1$
b10 I
b10 H
b10 G
b10 F
b10 D
b100 E
