james_files/RTL/mult_and_loader_v7_optimise/matrix.sv
`timescale 1 ns / 1 ps

module matrix(
    input CLK,
    input [63:0] flat_matrix_1,
    input [63:0] flat_matrix_2,
    input [3:0] R1,
    input [3:0] C1,
    input [3:0] R2,
    input [3:0] C2,
    input readybit,
    output reg [63:0] res_mat
);

    wire [15:0] num0a, num1a, num2a, num3a;
    wire [15:0] num0b, num1b, num2b, num3b;

    reg delay;

    always @* begin
        if (readybit) begin
            res_mat[63:48] <= num0a * num0b + num1a * num2b;
            res_mat[47:32] <= num0a * num1b + num1a * num3b;
            res_mat[31:16] <= num2a * num0b + num3a * num2b;
            res_mat[15:0]  <= num2a * num1b + num3a * num3b;
        end
    end

    assign num0a = flat_matrix_1[63:48];
    assign num1a = flat_matrix_1[47:32];
    assign num2a = flat_matrix_1[31:16];
    assign num3a = flat_matrix_1[15:0];

    assign num0b = flat_matrix_2[63:48];
    assign num1b = flat_matrix_2[47:32];
    assign num2b = flat_matrix_2[31:16];
    assign num3b = flat_matrix_2[15:0];

endmodule

james_files/RTL/mult_and_loader_v7_optimise/DflopX4.sv
`timescale 1 ns / 1 ps

module DflopX4(
    input wire CLK,
    input wire [7:0] a,
    output reg [7:0] x
    );

    always @(posedge CLK) begin
        x <= a;
    end

endmodule

james_files/RTL/mult_and_loader_v7_optimise/data_loader.sv
`timescale 1 ns / 1 ps

module data_loader(
    input wire CLK,
    input wire [7:0] data,
    input wire [1:0] ctrl_logic,
    output reg [63:0] res_mat
);
    reg [63:0] matrix_1;
    reg [63:0] matrix_2;

    reg [3:0] R1;
    reg [3:0] C1;

    reg [3:0] R2;
    reg [3:0] C2;

    reg [7:0] data_out;

    wire readybit;

    DflopX4 data_flop(CLK, data, data_out);
    matrix mult(CLK, matrix_1, matrix_2, R1, C1, R2, C2, readybit, res_mat);

    reg [1:0] count;
    reg [7:0] x, y;

    wire [3:0] y_max, x_max;

    initial begin
        count <= 0;
        x = 0;
        y = 0;
    end
    // always @(R1 or C1 or R2 or C2) begin
    //     //count <= count + 1;
    // end

    always @(posedge CLK) begin

    // size of matrix
        if (ctrl_logic == 1) begin
            case(count)
                3'h0: R1 <= data_out;
                3'h1: C1 <= data_out;
                3'h2: R2 <= data_out;
                3'h3: C2 <= data_out;
            endcase
            count <= count + 1;
        end else if(ctrl_logic == 0) begin // matrix data
            if(x < x_max) begin
                case(x)
                    8'd0: matrix_1[63:48] = data_out;
                    8'd1: matrix_1[47:32] = data_out;
                    8'd2: matrix_1[31:16] = data_out;
                    8'd3: matrix_1[15:0] = data_out;
                endcase
                //matrix_1[(15-x)*16 +: 16] = data_out;
                x = x + 1;
            end else if (y < y_max) begin 
                case(y)
                    8'd0: matrix_2[63:48] = data_out;
                    8'd1: matrix_2[47:32] = data_out;
                    8'd2: matrix_2[31:16] = data_out;
                    8'd3: matrix_2[15:0] = data_out;
                endcase
                y = y + 1;
            end
        end else if (ctrl_logic == 2) begin
            x = 0;
            y = 0;
            count <= 0;
        end
    end

    assign x_max = R1*C1;
    assign y_max = R2*C2;
    assign readybit = (x == x_max && y == y_max) ? 1'b1 : 1'b0;
endmodule

//matrix_4x4[(15-x)*16 +: 16] = data_out;  // Dynamic bit slicing
//x = x + 1;  // Increment x to fill the next element

james_files/RTL/mult_and_loader_v5_dc_shell/advanced_tb.sv
`timescale 1 ns / 1 ps

module advanced_tb();

    parameter NUM_MAT = 3; // set num of matrix to mult
    parameter MAT_SIZE = 4; // set num of matrix to mult
    parameter MAT_XxX = 2; // x by x size

    reg CLK;
    reg [1:0] ctrl_logic;
    reg [7:0] data_send;
    
    reg [7:0] load_data [0:127];
    reg [1:0] load_logic [0:255];

    reg [63:0] res_mat;

    wire S0;

    integer data_i, logic_i, count; // matrix indexes
    integer i, j, k;                // for loop ints

    reg testo;

    data_loader loader(CLK, data_send, ctrl_logic, res_mat);

    initial begin
        

        $dumpfile("waveform.vcd"); // Specifies the name of the dump file
        $dumpvars(0, advanced_tb);   // Dumps all variables in the module "testbench" and its submodules
        CLK = 0;
        count = 0;
        logic_i = 0;
        data_i  = 0;

        ctrl_logic = 1;
        data_send = 2;

        // load data for NUM_MAT of MAT_SIZE * 2, (*2 for 2 matrix per mult)
        for(i = 0; i < NUM_MAT * MAT_SIZE * 2; i++ ) begin
            load_data[i] = $random;
        end
        // load ctrl logic,
        for(i = 0; i < NUM_MAT*14; i++ ) begin

            load_logic[i] = 2;
            i = i + 1;
                
            for(j = 0; j < 4; j++) begin
                load_logic[i] = 1;
                i = i + 1;
            end
            for(j = 0; j < 2*MAT_SIZE; j++) begin
                load_logic[i] = 0;
                i = i + 1;
            end
            load_logic[i] = 2;
        end

        // for(i = 0; i < NUM_MAT*8; i++)
        //     $display(load_data[i]);
        // $display("---------------------------------------------------------");
        //  for(i = 0; i < NUM_MAT*14; i++)
        //      $display(load_logic[i]);

        forever #0.5 CLK = ~CLK;
    end

    //always #5 CLK=~CLK; //clock toggle every 0.5 ns

    always @(posedge CLK) begin

        ctrl_logic <= load_logic[logic_i++];
        case(count)
            8'h0:
                data_send <= MAT_XxX;
            8'h1:
                data_send <= MAT_XxX;
            8'h2:
                data_send <= MAT_XxX;
            8'h3: 
                data_send <= MAT_XxX;
            8'h4: begin
                data_send <= load_data[data_i];
                data_i = data_i + 1;
            end
            8'h5: begin
                data_send <= load_data[data_i];
                data_i = data_i + 1;
            end
            8'h6: begin
                data_send <= load_data[data_i];
                data_i = data_i + 1;
            end
            8'h7: begin
                data_send <= load_data[data_i];
                data_i = data_i + 1;
            end
            8'h8: begin
                data_send <= load_data[data_i];
                data_i = data_i + 1;
            end
            8'h9: begin
                data_send <= load_data[data_i];
                data_i = data_i + 1;
            end
            8'hA: begin
                data_send <= load_data[data_i];
                data_i = data_i + 1;
            end
            8'hB: begin
                data_send <= load_data[data_i];
                data_i = data_i + 1;
            end
            8'hC:
                data_send <= 0;
            8'hD:
                data_send <= 0;
        endcase
        
        // || (logic_i == 14 & count == 14)
        if(count == 13) begin
            count = 0;
            #5
            $display("--- result ---");
            $display(res_mat[63:48]," ", res_mat[47:32]);
            $display(res_mat[31:16]," ", res_mat[15:0]);
        end else begin
            count = count + 1;
        end

        if(logic_i == 14*NUM_MAT) begin
            #10
            $finish;
        end 
    end
endmodule

james_files/RTL/mult_and_loader_v7_optimise/waveform.vcd
$date
	Wed May 08 18:46:32 2024
$end
$version
	Icarus Verilog
$end
$timescale
	1ps
$end
$scope module advanced_tb $end
$var wire 64 ! res_mat [63:0] $end
$var parameter 32 " MAT_SIZE $end
$var parameter 32 # MAT_XxX $end
$var parameter 32 $ NUM_MAT $end
$var reg 1 % CLK $end
$var reg 2 & ctrl_logic [1:0] $end
$var reg 8 ' data_send [7:0] $end
$var integer 32 ( count [31:0] $end
$var integer 32 ) data_i [31:0] $end
$var integer 32 * i [31:0] $end
$var integer 32 + j [31:0] $end
$var integer 32 , logic_i [31:0] $end
$scope module loader $end
$var wire 1 % CLK $end
$var wire 2 - ctrl_logic [1:0] $end
$var wire 8 . data [7:0] $end
$var wire 4 / y_max [3:0] $end
$var wire 4 0 x_max [3:0] $end
$var wire 64 1 res_mat [63:0] $end
$var wire 1 2 readybit $end
$var wire 8 3 data_out [7:0] $end
$var reg 4 4 C1 [3:0] $end
$var reg 4 5 C2 [3:0] $end
$var reg 4 6 R1 [3:0] $end
$var reg 4 7 R2 [3:0] $end
$var reg 2 8 count [1:0] $end
$var reg 64 9 matrix_1 [63:0] $end
$var reg 64 : matrix_2 [63:0] $end
$var reg 8 ; x [7:0] $end
$var reg 8 < y [7:0] $end
$scope module data_flop $end
$var wire 1 % CLK $end
$var wire 8 = a [7:0] $end
$var reg 8 > x [7:0] $end
$upscope $end
$scope module mult $end
$var wire 4 ? C1 [3:0] $end
$var wire 4 @ C2 [3:0] $end
$var wire 1 % CLK $end
$var wire 4 A R1 [3:0] $end
$var wire 4 B R2 [3:0] $end
$var wire 64 C flat_matrix_1 [63:0] $end
$var wire 64 D flat_matrix_2 [63:0] $end
$var wire 1 2 readybit $end
$var wire 16 E num3b [15:0] $end
$var wire 16 F num3a [15:0] $end
$var wire 16 G num2b [15:0] $end
$var wire 16 H num2a [15:0] $end
$var wire 16 I num1b [15:0] $end
$var wire 16 J num1a [15:0] $end
$var wire 16 K num0b [15:0] $end
$var wire 16 L num0a [15:0] $end
$var reg 64 M res_mat [63:0] $end
$upscope $end
$upscope $end
$upscope $end
$enddefinitions $end
$comment Show the parameter values. $end
$dumpall
b11 $
b10 #
b100 "
$end
#0
$dumpvars
bx M
bx L
bx K
bx J
bx I
bx H
bx G
bx F
bx E
bx D
bx C
bx B
bx A
bx @
bx ?
bx >
b10 =
b0 <
b0 ;
bx :
bx 9
b0 8
bx 7
bx 6
bx 5
bx 4
bx 3
x2
bx 1
bx 0
bx /
b10 .
b1 -
b0 ,
b1000 +
b101010 *
b0 )
b0 (
b10 '
b1 &
0%
bx !
$end
#500
b10 3
b10 >
b1 8
b10 &
b10 -
b1 (
b1 ,
1%
#1000
0%
#1500
b1 &
b1 -
b0 8
b10 (
b10 ,
1%
#2000
0%
#2500
b1 8
b10 6
b10 A
b11 (
b11 ,
1%
#3000
0%
#3500
02
b10 8
b100 0
b10 4
b10 ?
b100 (
b100 ,
1%
#4000
0%
#4500
b11 8
b10 7
b10 B
b100100 '
b100100 .
b100100 =
b101 (
b1 )
b101 ,
1%
#5000
0%
#5500
b10000001 '
b10000001 .
b10000001 =
b0 &
b0 -
b0 8
b100 /
b10 5
b10 @
b100100 3
b100100 >
b110 (
b10 )
b110 ,
1%
#6000
0%
#6500
b10000001 3
b10000001 >
b1001 '
b1001 .
b1001 =
b100100 L
b1 ;
b100100xxxxxxxxxxxxxxxxxxxxxxxxxxxxxxxxxxxxxxxxxxxxxxxx 9
b100100xxxxxxxxxxxxxxxxxxxxxxxxxxxxxxxxxxxxxxxxxxxxxxxx C
b111 (
b11 )
b111 ,
1%
#7000
0%
#7500
b1100011 '
b1100011 .
b1100011 =
b1001 3
b1001 >
b10000001 J
b1000 (
b100 )
b1000 ,
b10 ;
b1001000000000010000001xxxxxxxxxxxxxxxxxxxxxxxxxxxxxxxx 9
b1001000000000010000001xxxxxxxxxxxxxxxxxxxxxxxxxxxxxxxx C
1%
#8000
0%
#8500
b1100011 3
b1100011 >
b1101 '
b1101 .
b1101 =
b1001 H
b11 ;
b10010000000000100000010000000000001001xxxxxxxxxxxxxxxx 9
b10010000000000100000010000000000001001xxxxxxxxxxxxxxxx C
b1001 (
b101 )
b1001 ,
1%
#9000
0%
#9500
b10001101 '
b10001101 .
b10001101 =
b1101 3
b1101 >
b1100011 F
b1010 (
b110 )
b1010 ,
b100 ;
b100100000000001000000100000000000010010000000001100011 9
b100100000000001000000100000000000010010000000001100011 C
1%
#10000
0%
#10500
b10001101 3
b10001101 >
b1100101 '
b1100101 .
b1100101 =
b1101 K
b1 <
b1101xxxxxxxxxxxxxxxxxxxxxxxxxxxxxxxxxxxxxxxxxxxxxxxx :
b1101xxxxxxxxxxxxxxxxxxxxxxxxxxxxxxxxxxxxxxxxxxxxxxxx D
b1011 (
b111 )
b1011 ,
1%
#11000
0%
#11500
b10010 '
b10010 .
b10010 =
b1100101 3
b1100101 >
b10001101 I
b1100 (
b1000 )
b1100 ,
b10 <
b11010000000010001101xxxxxxxxxxxxxxxxxxxxxxxxxxxxxxxx :
b11010000000010001101xxxxxxxxxxxxxxxxxxxxxxxxxxxxxxxx D
1%
#12000
0%
#12500
b10010 3
b10010 >
b0 '
b0 .
b0 =
b1100101 G
b11 <
b110100000000100011010000000001100101xxxxxxxxxxxxxxxx :
b110100000000100011010000000001100101xxxxxxxxxxxxxxxx D
b1101 (
b1101 ,
1%
#13000
0%
#13500
b11010010111001000111001110011000100111100001000000101111101011 !
b11010010111001000111001110011000100111100001000000101111101011 1
b11010010111001000111001110011000100111100001000000101111101011 M
b10 &
b10 -
b0 3
b0 >
12
b10010 E
b0 (
b1110 ,
b100 <
b1101000000001000110100000000011001010000000000010010 :
b1101000000001000110100000000011001010000000000010010 D
1%
#14000
0%
#14500
02
b0 <
b0 ;
1%
#15000
0%
#15500
1%
#16000
0%
#16500
1%
#17000
0%
#17500
1%
#18000
0%
#18500
b10 '
b10 .
b10 =
b1 (
b1111 ,
1%
#19000
0%
#19500
b1 &
b1 -
b10 3
b10 >
b10 (
b10000 ,
1%
#20000
0%
#20500
b1 8
b11 (
b10001 ,
1%
#21000
0%
#21500
b10 8
b100 (
b10010 ,
1%
#22000
0%
#22500
b11 8
b1 '
b1 .
b1 =
b101 (
b1001 )
b10011 ,
1%
#23000
0%
#23500
b1101 '
b1101 .
b1101 =
b0 &
b0 -
b0 8
b1 3
b1 >
b110 (
b1010 )
b10100 ,
1%
#24000
0%
#24500
b1101 3
b1101 >
b1110110 '
b1110110 .
b1110110 =
b1 L
b1 ;
b1000000001000000100000000000010010000000001100011 9
b1000000001000000100000000000010010000000001100011 C
b111 (
b1011 )
b10101 ,
1%
#25000
0%
#25500
b111101 '
b111101 .
b111101 =
b1110110 3
b1110110 >
b1101 J
b1000 (
b1100 )
b10110 ,
b10 ;
b1000000000000110100000000000010010000000001100011 9
b1000000000000110100000000000010010000000001100011 C
1%
#26000
0%
#26500
b111101 3
b111101 >
b11101101 '
b11101101 .
b11101101 =
b1110110 H
b11 ;
b1000000000000110100000000011101100000000001100011 9
b1000000000000110100000000011101100000000001100011 C
b1001 (
b1101 )
b10111 ,
1%
#27000
0%
#27500
b10001100 '
b10001100 .
b10001100 =
b11101101 3
b11101101 >
b111101 F
b1010 (
b1110 )
b11000 ,
b100 ;
b1000000000000110100000000011101100000000000111101 9
b1000000000000110100000000011101100000000000111101 C
1%
#28000
0%
#28500
b10001100 3
b10001100 >
b11111001 '
b11111001 .
b11111001 =
b11101101 K
b1 <
b11101101000000001000110100000000011001010000000000010010 :
b11101101000000001000110100000000011001010000000000010010 D
b1011 (
b1111 )
b11001 ,
1%
#29000
0%
#29500
b11000110 '
b11000110 .
b11000110 =
b11111001 3
b11111001 >
b10001100 I
b1100 (
b10000 )
b11010 ,
b10 <
b11101101000000001000110000000000011001010000000000010010 :
b11101101000000001000110000000000011001010000000000010010 D
1%
#30000
0%
#30500
b11000110 3
b11000110 >
b0 '
b0 .
b0 =
b11111001 G
b11 <
b11101101000000001000110000000000111110010000000000010010 :
b11101101000000001000110000000000111110010000000000010010 D
b1101 (
b11011 ,
1%
#31000
0%
#31500
b110110010010000010101001101010101000100100110110111110110110 !
b110110010010000010101001101010101000100100110110111110110110 1
b110110010010000010101001101010101000100100110110111110110110 M
b10 &
b10 -
b0 3
b0 >
12
b11000110 E
b0 (
b11100 ,
b100 <
b11101101000000001000110000000000111110010000000011000110 :
b11101101000000001000110000000000111110010000000011000110 D
1%
#32000
0%
#32500
02
b0 <
b0 ;
1%
#33000
0%
#33500
1%
#34000
0%
#34500
1%
#35000
0%
#35500
1%
#36000
0%
#36500
b10 '
b10 .
b10 =
b1 (
b11101 ,
1%
#37000
0%
#37500
b1 &
b1 -
b10 3
b10 >
b10 (
b11110 ,
1%
#38000
0%
#38500
b1 8
b11 (
b11111 ,
1%
#39000
0%
#39500
b10 8
b100 (
b100000 ,
1%
#40000
0%
#40500
b11 8
b11000101 '
b11000101 .
b11000101 =
b101 (
b10001 )
b100001 ,
1%
#41000
0%
#41500
b10101010 '
b10101010 .
b10101010 =
b0 &
b0 -
b0 8
b11000101 3
b11000101 >
b110 (
b10010 )
b100010 ,
1%
#42000
0%
#42500
b10101010 3
b10101010 >
b11100101 '
b11100101 .
b11100101 =
b11000101 L
b1 ;
b11000101000000000000110100000000011101100000000000111101 9
b11000101000000000000110100000000011101100000000000111101 C
b111 (
b10011 )
b100011 ,
1%
#43000
0%
#43500
b1110111 '
b1110111 .
b1110111 =
b11100101 3
b11100101 >
b10101010 J
b1000 (
b10100 )
b100100 ,
b10 ;
b11000101000000001010101000000000011101100000000000111101 9
b11000101000000001010101000000000011101100000000000111101 C
1%
#44000
0%
#44500
b1110111 3
b1110111 >
b10010 '
b10010 .
b10010 =
b11100101 H
b11 ;
b11000101000000001010101000000000111001010000000000111101 9
b11000101000000001010101000000000111001010000000000111101 C
b1001 (
b10101 )
b100101 ,
1%
#45000
0%
#45500
b10001111 '
b10001111 .
b10001111 =
b10010 3
b10010 >
b1110111 F
b1010 (
b10110 )
b100110 ,
b100 ;
b11000101000000001010101000000000111001010000000001110111 9
b11000101000000001010101000000000111001010000000001110111 C
1%
#46000
0%
#46500
b10001111 3
b10001111 >
b11110010 '
b11110010 .
b11110010 =
b10010 K
b1 <
b10010000000001000110000000000111110010000000011000110 :
b10010000000001000110000000000111110010000000011000110 D
b1011 (
b10111 )
b100111 ,
1%
#47000
0%
#47500
b11001110 '
b11001110 .
b11001110 =
b11110010 3
b11110010 >
b10001111 I
b1100 (
b11000 )
b101000 ,
b10 <
b10010000000001000111100000000111110010000000011000110 :
b10010000000001000111100000000111110010000000011000110 D
1%
#48000
0%
#48500
b11001110 3
b11001110 >
b0 '
b0 .
b0 =
b11110010 G
b11 <
b10010000000001000111100000000111100100000000011000110 :
b10010000000001000111100000000111100100000000011000110 D
b1101 (
b101001 ,
1%
#49000
0%
#49500
b1010111010001110111101101101011110000000100110001101111110101101 !
b1010111010001110111101101101011110000000100110001101111110101101 1
b1010111010001110111101101101011110000000100110001101111110101101 M
b10 &
b10 -
b0 3
b0 >
12
b11001110 E
b0 (
b101010 ,
b100 <
b10010000000001000111100000000111100100000000011001110 :
b10010000000001000111100000000111100100000000011001110 D
1%
#50000
0%
#50500
02
b0 <
b0 ;
1%
