james_files/vs1/data_loader_v2/DflopX4.sv
`timescale 1 ns / 1 ps

module DflopX4(
    input wire CLK,
    input wire [3:0] a,
    output reg [3:0] x
);

always @(posedge clk) begin
    x <= a;
end

endmodule

james_files/vs1/data_loader_v2/data_loader.sv
`timescale 1 ns / 1 ps

module matrix(
    input wire CLK,
    input wire [3:0] data,
    input wire ctrl_logic
);

    parameter Y_DIM = 2;
    parameter X_DIM = 2;

    reg [31:0] matrix_1 [0:Y_DIM][0:X_DIM];
    reg [31:0] matrix_2 [0:Y_DIM][0:X_DIM];

    reg [3:0] R1;
    reg [3:0] C1;

    reg [3:0] R2;
    reg [3:0] C2;

    reg [3:0] data_out;

    reg testFlop;


    DflopX4 data_flop(CLK, data, data_out);

    integer count, x, y;

    initial begin
        count = 0;
        x = 0;
        y = 0;
    end
    
    always @(posedge CLK) begin
        //$display(testFlop , "<=", data[0]);

       // $display("recieved ", data, " Flopped to ", data_out, " logic: ", ctrl_logic);

        // size of matrix
        if (ctrl_logic == 1) begin
            case(count)
                3'h1: R1 <= data_out;
                3'h2: C1 <= data_out;
                3'h3: R2 <= data_out;
                3'h4: C2 <= data_out;
            endcase
            count++;
        end else begin // matrix data
            //$display("data_out: ", data_out, " yx: ", y,x);
            matrix_1[y][x] = data_out;
            //$display("matrix val: ", matrix_1[y][x]);
            x = x + 1;
            if(x >= R1 && y < C1) begin
                x = 0;
                y = y + 1;
            end
        end   
    end

endmodule

james_files/vs1/data_loader_v2/data_loader_tb.sv
`timescale 1 ns / 1 ps

module data_loader_tb();

    reg CLK, ctrl_logic;
    reg [3:0] data_send;
    integer count;
    wire S0;

    matrix loader(CLK, data_send, ctrl_logic);
    initial begin

        $dumpfile("waveform.vcd"); // Specifies the name of the dump file
        $dumpvars(0, data_loader_tb);   // Dumps all variables in the module "testbench" and its submodules
        //$dumpvars(1, data_loader_tb.x1); // For a specific submodule
        //$dumpvars(0, matrix);   // Dumps all variables in the module "testbench" and its submodules
        CLK = 0;
        count = 0;
        data_send = 2;
        ctrl_logic = 1;
        forever #1 CLK = ~CLK;
    end

    //always #5 CLK=~CLK; //clock toggle every 0.5 ns

    always @(posedge CLK) begin
        case(count)
            4'h0: begin
                data_send <= 2;
                ctrl_logic <= 1;
            end
            4'h1: begin
                data_send <= 2;
                ctrl_logic <= 1;
            end
            4'h2: begin
                data_send <= 2;
                ctrl_logic <= 1;
            end
            4'h3: begin
                data_send <= 2;
                ctrl_logic <= 1;
            end
            4'h4: begin
                data_send <= 1;
                ctrl_logic <= 0;
            end
            4'h5: begin
                data_send <= 15;
                ctrl_logic <= 0;
            end
            4'h6: begin
                data_send <= 2;
                ctrl_logic <= 0;
            end
            4'h7: begin
                #5
                $display("matrix loaded");
                $display(loader.matrix_1[0][0], loader.matrix_1[0][1]);
                $display(loader.matrix_1[1][0], loader.matrix_1[1][1],);
                $display("size");
                $display("R1: ", loader.R1, " C1: ", loader.C1);
                $display("R2: ", loader.R2, " C2: ", loader.C2);
                $finish;
            end
        endcase
        count++;
    end


endmodule

james_files/vs1/data_loader_v2/waveform.vcd
$date
	Sat Apr 13 12:49:18 2024
$end
$version
	Icarus Verilog
$end
$timescale
	1ps
$end
$scope module data_loader_tb $end
$var reg 1 ! CLK $end
$var reg 1 " ctrl_logic $end
$var reg 4 # data_send [3:0] $end
$var integer 32 $ count [31:0] $end
$scope module loader $end
$var wire 1 ! CLK $end
$var wire 1 " ctrl_logic $end
$var wire 4 % data [3:0] $end
$var wire 4 & data_out [3:0] $end
$var parameter 32 ' X_DIM $end
$var parameter 32 ( Y_DIM $end
$var reg 4 ) C1 [3:0] $end
$var reg 4 * C2 [3:0] $end
$var reg 4 + R1 [3:0] $end
$var reg 4 , R2 [3:0] $end
$var integer 32 - count [31:0] $end
$var integer 32 . x [31:0] $end
$var integer 32 / y [31:0] $end
$scope module data_flop $end
$var wire 1 ! CLK $end
$var wire 4 0 a [3:0] $end
$var reg 4 1 x [3:0] $end
$upscope $end
$upscope $end
$upscope $end
$enddefinitions $end
$comment Show the parameter values. $end
$dumpall
b10 (
b10 '
$end
#0
$dumpvars
bx 1
b10 0
b0 /
b0 .
b0 -
bx ,
bx +
bx *
bx )
bx &
b10 %
b0 $
b10 #
1"
0!
$end
#1000
b10 &
b10 1
b1 -
b1 $
1!
#2000
0!
#3000
b10 +
b10 $
b10 -
1!
#4000
0!
#5000
b10 )
b11 -
b11 $
1!
#6000
0!
#7000
b10 ,
b100 $
b100 -
1!
#8000
0!
#9000
b10 *
0"
b1 #
b1 %
b1 0
b101 -
b101 $
1!
#10000
0!
#11000
b1111 #
b1111 %
b1111 0
b1 &
b1 1
b110 $
b1 .
1!
#12000
0!
#13000
b1111 &
b1111 1
b10 #
b10 %
b10 0
b1 /
b0 .
b111 $
1!
#14000
0!
#15000
b10 &
b10 1
b1 .
1!
#16000
0!
#17000
b10 /
b0 .
1!
#18000
0!
#19000
b1 .
1!
