james_files/vs1/data_loader/data_loader.sv
`timescale 1 ns / 1 ps

module matrix(
    input wire CLK,
    input wire [3:0] data,
    input wire ctrl_logic
);

    parameter Y_DIM = 2;
    parameter X_DIM = 2;

    reg [31:0] matrix_1 [0:Y_DIM][0:X_DIM];
    reg [31:0] matrix_2 [0:Y_DIM][0:X_DIM];

    reg [3:0] R1;
    reg [3:0] C1;

    reg [3:0] R2;
    reg [3:0] C2;


    integer count, x, y;

    initial begin
        count = 0;
        x = 0;
        y = 0;
    end

    always @(posedge CLK) begin
        //$display("Recieved a ", data);
        #0.001

        // size of matrix
        if (ctrl_logic == 1) begin
            case(count)
                2'b00: R1 <= data;
                2'b01: C1 <= data;
                2'b10: R2 <= data;
                2'b11: C2 <= data;
            endcase
            count++;
        end else begin // matrix data
            $display("data ", data, " ", y,x);
            matrix_1[y][x] <= data;
            //$display(matrix_1[y][x], " ", data);
            x = x + 1;
            if(x >= R1 && y < C1) begin
                x = 0;
                y = y + 1;
                //$display("change x/y");
            end else begin
                //$display("R1 = ", R1, " C1 = ", C1);
            end
        end   
    end

endmodule

james_files/vs1/data_loader/data_loader_tb.sv
`timescale 1 ns / 1 ps

module data_loader_tb();

    reg CLK, ctrl_logic;
    reg [3:0] data_send;
    integer count;
    wire S0;

    matrix x1(CLK, data_send, ctrl_logic);
    initial begin

        $dumpfile("waveform.vcd"); // Specifies the name of the dump file
        $dumpvars(0, data_loader_tb);   // Dumps all variables in the module "testbench" and its submodules
        //$dumpvars(1, data_loader_tb.x1); // For a specific submodule
        //$dumpvars(0, matrix);   // Dumps all variables in the module "testbench" and its submodules
        CLK = 0;
        count = 0;
        data_send = 0;
        ctrl_logic = 0;

        
    end

    always #0.5 CLK=~CLK; //clock toggle every 0.5 ns

    always @(posedge CLK) begin
        case(count)
            4'h0: begin
                data_send = 2;
                ctrl_logic = 1;
            end
            4'h1: begin
                data_send = 3;
                ctrl_logic = 1;
            end
            4'h2: begin
                data_send = 2;
                ctrl_logic = 1;
            end
            4'h3: begin
                data_send = 1;
                ctrl_logic = 1;
            end
            4'h4: begin
                data_send = 0;
                ctrl_logic = 0;
            end
            4'h5: begin
                data_send = 9;
                ctrl_logic = 0;
            end
            4'h6: begin
                data_send = 7;
                ctrl_logic = 0;
            end
            4'h7: begin
                data_send = 4;
                ctrl_logic = 0;
            end
            4'h8: begin

                $display("matrix loaded");
                $display(x1.matrix_1[0][0], x1.matrix_1[0][1]);
                $display(x1.matrix_1[1][0], x1.matrix_1[1][1],);
                $display("size");
                $display("R1: ", x1.R1, " C1: ", x1.C1);
                $display("R2: ", x1.R2, " C2: ", x1.C2);
                $finish;

            end
        endcase
        count++;
    end


endmodule

james_files/vs1/data_loader/waveform.vcd
$date
	Tue Apr 09 12:49:44 2024
$end
$version
	Icarus Verilog
$end
$timescale
	1ps
$end
$scope module data_loader_tb $end
$var reg 1 ! CLK $end
$var reg 1 " ctrl_logic $end
$var reg 4 # data_send [3:0] $end
$var integer 32 $ count [31:0] $end
$scope module x1 $end
$var wire 1 ! CLK $end
$var wire 1 " ctrl_logic $end
$var wire 4 % data [3:0] $end
$var parameter 32 & X_DIM $end
$var parameter 32 ' Y_DIM $end
$var reg 4 ( C1 [3:0] $end
$var reg 4 ) C2 [3:0] $end
$var reg 4 * R1 [3:0] $end
$var reg 4 + R2 [3:0] $end
$var integer 32 , count [31:0] $end
$var integer 32 - x [31:0] $end
$var integer 32 . y [31:0] $end
$upscope $end
$upscope $end
$enddefinitions $end
$comment Show the parameter values. $end
$dumpall
b10 '
b10 &
$end
#0
$dumpvars
b0 .
b0 -
b0 ,
bx +
bx *
bx )
bx (
b0 %
b0 $
b0 #
0"
0!
$end
#500
b10 *
b1 ,
b1 $
1"
b10 #
b10 %
1!
#1000
0!
#1500
b10 (
b10 $
b11 #
b11 %
b10 ,
1!
#2000
0!
#2500
b10 +
b11 ,
b11 $
b10 #
b10 %
1!
#3000
0!
#3500
b10 )
b100 $
b1 #
b1 %
b100 ,
1!
#4000
0!
#4500
b1 -
b101 $
0"
b0 #
b0 %
1!
#5000
0!
#5500
b110 $
b1001 #
b1001 %
b1 .
b0 -
1!
#6000
0!
#6500
b1 -
b111 $
b111 #
b111 %
1!
#7000
0!
#7500
b1000 $
b100 #
b100 %
b10 .
b0 -
1!
