ryan_files/pipelined_multiplier/rtl/matrix_pipeline.v
module MatrixMultiplier (
    input wire clk,        // Clock signal
    input wire rst,        // Reset signal
    input wire [7:0] loaded_num_a0, loaded_num_a1, loaded_num_a2, loaded_num_a3,  // Input matrix A
    input wire [7:0] loaded_num_b0, loaded_num_b1, loaded_num_b2, loaded_num_b3,  // Input matrix B
    
    output reg [15:0] result1, result2, result3, result4,         // Output matrix C
    output reg matrix_multiplication_done                         // Multiplication done signal
);
reg [3:0] i;

// Declare reg outputs
//reg [15:0] result1_reg, result2_reg, result3_reg, result4_reg;

// Intermediate signals
reg [15:0] intermediate_result_0;
reg [15:0] intermediate_result_1;
reg [15:0] intermediate_result_2;
reg [15:0] intermediate_result_3;
reg [15:0] intermediate_result_4;
reg [15:0] intermediate_result_5;
reg [15:0] intermediate_result_6;
reg [15:0] intermediate_result_7;

// Pipeline stage control signals
reg [3:0] pipeline_stage;

// Reset and initialization
always @(posedge clk or posedge rst) begin
     if (rst) begin
          // Reset registers
          result1 <= 0;
          result2 <= 0;
          result3 <= 0;
          result4 <= 0;

          // Reset intermediate result
          intermediate_result_0 <= 0;
          intermediate_result_1 <= 0;
          intermediate_result_2 <= 0;
          intermediate_result_3 <= 0;
          intermediate_result_4 <= 0;
          intermediate_result_5 <= 0;
          intermediate_result_6 <= 0;
          intermediate_result_7 <= 0;

          // Reset pipeline stage control & matrix_multiplication_done signal
          pipeline_stage <= 4'b0000;
          matrix_multiplication_done <= 0;

    end else begin
          // start of multiplication and accumulation pipeline
          case(pipeline_stage)
               4'b0000: begin // Stage 0
                    intermediate_result_0 <= loaded_num_a0 * loaded_num_b0;
                    intermediate_result_1 <= loaded_num_a1 * loaded_num_b2;   
                    pipeline_stage <= 4'b0001; 
               end
               4'b0001: begin // Stage 1
                    intermediate_result_2 <= loaded_num_a0 * loaded_num_b1;
                    intermediate_result_3 <= loaded_num_a1 * loaded_num_b3;                    
                    pipeline_stage <= 4'b0010; 
               end
               4'b0010: begin // Stage 2
                    intermediate_result_4 <= loaded_num_a2 * loaded_num_b0;
                    intermediate_result_5 <= loaded_num_a3 * loaded_num_b2;
                    pipeline_stage <= 4'b0011; 
               end
               4'b0011: begin // Stage 3
                    intermediate_result_6 <= loaded_num_a2 * loaded_num_b1;
                    intermediate_result_7 <= loaded_num_a3 * loaded_num_b3;
                    pipeline_stage <= 4'b0100; 
               end
               4'b0100: begin // Stage 4
                    result1 <= intermediate_result_0 + intermediate_result_1;
                    result2 <= intermediate_result_2 + intermediate_result_3;
                    result3 <= intermediate_result_4 + intermediate_result_5;
                    result4 <= intermediate_result_6 + intermediate_result_7;
                    pipeline_stage <= 4'b0101; 
               end
          endcase
     end
end

endmodule

ryan_files/pipelined_multiplier/rtl/loader.v
module NumberLoader (
    input wire clk,
    input wire [31:0] nums_a,
    input wire [31:0] nums_b,
    output reg [7:0] loaded_num_a0,
    output reg [7:0] loaded_num_a1,
    output reg [7:0] loaded_num_a2,
    output reg [7:0] loaded_num_a3,
    output reg [7:0] loaded_num_b0,
    output reg [7:0] loaded_num_b1,
    output reg [7:0] loaded_num_b2,
    output reg [7:0] loaded_num_b3,
    input wire load
);

    always @(posedge clk) begin
        if (load) begin // load enable control bit
            loaded_num_a0 <= nums_a[31:24];
            loaded_num_a1 <= nums_a[23:16];
            loaded_num_a2 <= nums_a[15:8];
            loaded_num_a3 <= nums_a[7:0];

            loaded_num_b0 <= nums_b[31:24];
            loaded_num_b1 <= nums_b[23:16];
            loaded_num_b2 <= nums_b[15:8];
            loaded_num_b3 <= nums_b[7:0];
        end
    end

endmodule

ryan_files/pipelined_multiplier/rtl/testbench.v
`timescale 1ns/1ps

module testbench ();

    parameter CLOCK_PERIOD = 1;

    // Inputs
    reg clk = 0 ;
    reg rst = 0; // Reset control
    reg load;
    reg [31:0] nums_a;
    reg [31:0] nums_b;

    // Outputs
    wire [15:0] result [1:4];
    wire [7:0] loaded_num_a0, loaded_num_a1, loaded_num_a2, loaded_num_a3;
    wire [7:0] loaded_num_b0, loaded_num_b1, loaded_num_b2, loaded_num_b3;
    wire matrix_multiplication_done;

    // Instantiate NumberLoader
    NumberLoader loader (
        .clk(clk),
        .nums_a(nums_a),                
        .nums_b(nums_b),                
        .loaded_num_a0(loaded_num_a0), 
        .loaded_num_a1(loaded_num_a1),
        .loaded_num_a2(loaded_num_a2),
        .loaded_num_a3(loaded_num_a3),
        .loaded_num_b0(loaded_num_b0), 
        .loaded_num_b1(loaded_num_b1),
        .loaded_num_b2(loaded_num_b2),
        .loaded_num_b3(loaded_num_b3),
        .load(load)                     
    );

        MatrixMultiplier multiplier (
        .clk(clk),
        .rst(rst),
        .loaded_num_a0(loaded_num_a0),
        .loaded_num_a1(loaded_num_a1),
        .loaded_num_a2(loaded_num_a2),
        .loaded_num_a3(loaded_num_a3),
        .loaded_num_b0(loaded_num_b0),
        .loaded_num_b1(loaded_num_b1),
        .loaded_num_b2(loaded_num_b2),
        .loaded_num_b3(loaded_num_b3),
        .result1(result[1]),
        .result2(result[2]),
        .result3(result[3]),
        .result4(result[4]),
        .matrix_multiplication_done(matrix_multiplication_done)
    );

    // Generate clock
    always #1 clk = ~clk;

    // Testbench
    initial begin
        $dumpfile("simulation.vcd");
        $dumpvars(0, testbench);

        // Test bits
        //Row-wise:  R1C1,         R1C2,        R2C1,        R2C2
        nums_a = {8'b00000001, 8'b00000010, 8'b00000100, 8'b00001000};
        nums_b = {8'b00000001, 8'b00000011, 8'b00000101, 8'b00001011};
        
        // Start loading
        load = 1;
        #5;
        load = 0;
        #2;
        
        // Reset signal asserted
        rst = 1;
        #2;
        rst = 0;

        // End simulation
        #100;
        $finish;
    end

endmodule

ryan_files/pipelined_multiplier/sim/simulation.vcd
$date
	Fri Apr 19 11:35:47 2024
$end
$version
	ModelSim Version 2022.3
$end
$timescale
	1ps
$end

$scope module testbench $end
$var parameter 32 ! CLOCK_PERIOD $end
$var reg 1 " clk $end
$var reg 1 # rst $end
$var reg 1 $ load $end
$var reg 32 % nums_a [31:0] $end
$var reg 32 & nums_b [31:0] $end
$var wire 1 ' result [0] $end
$var wire 1 ( result [1] $end
$var wire 1 ) result [2] $end
$var wire 1 * result [3] $end
$var wire 1 + result [4] $end
$var wire 1 , result [5] $end
$var wire 1 - result [6] $end
$var wire 1 . result [7] $end
$var wire 1 / result [8] $end
$var wire 1 0 result [9] $end
$var wire 1 1 result [10] $end
$var wire 1 2 result [11] $end
$var wire 1 3 result [12] $end
$var wire 1 4 result [13] $end
$var wire 1 5 result [14] $end
$var wire 1 6 result [15] $end
$var wire 1 7 result [16] $end
$var wire 1 8 result [17] $end
$var wire 1 9 result [18] $end
$var wire 1 : result [19] $end
$var wire 1 ; result [20] $end
$var wire 1 < result [21] $end
$var wire 1 = result [22] $end
$var wire 1 > result [23] $end
$var wire 1 ? result [24] $end
$var wire 1 @ result [25] $end
$var wire 1 A result [26] $end
$var wire 1 B result [27] $end
$var wire 1 C result [28] $end
$var wire 1 D result [29] $end
$var wire 1 E result [30] $end
$var wire 1 F result [31] $end
$var wire 1 G result [32] $end
$var wire 1 H result [33] $end
$var wire 1 I result [34] $end
$var wire 1 J result [35] $end
$var wire 1 K result [36] $end
$var wire 1 L result [37] $end
$var wire 1 M result [38] $end
$var wire 1 N result [39] $end
$var wire 1 O result [40] $end
$var wire 1 P result [41] $end
$var wire 1 Q result [42] $end
$var wire 1 R result [43] $end
$var wire 1 S result [44] $end
$var wire 1 T result [45] $end
$var wire 1 U result [46] $end
$var wire 1 V result [47] $end
$var wire 1 W result [48] $end
$var wire 1 X result [49] $end
$var wire 1 Y result [50] $end
$var wire 1 Z result [51] $end
$var wire 1 [ result [52] $end
$var wire 1 \ result [53] $end
$var wire 1 ] result [54] $end
$var wire 1 ^ result [55] $end
$var wire 1 _ result [56] $end
$var wire 1 ` result [57] $end
$var wire 1 a result [58] $end
$var wire 1 b result [59] $end
$var wire 1 c result [60] $end
$var wire 1 d result [61] $end
$var wire 1 e result [62] $end
$var wire 1 f result [63] $end
$var wire 1 g loaded_num_a0 [7] $end
$var wire 1 h loaded_num_a0 [6] $end
$var wire 1 i loaded_num_a0 [5] $end
$var wire 1 j loaded_num_a0 [4] $end
$var wire 1 k loaded_num_a0 [3] $end
$var wire 1 l loaded_num_a0 [2] $end
$var wire 1 m loaded_num_a0 [1] $end
$var wire 1 n loaded_num_a0 [0] $end
$var wire 1 o loaded_num_a1 [7] $end
$var wire 1 p loaded_num_a1 [6] $end
$var wire 1 q loaded_num_a1 [5] $end
$var wire 1 r loaded_num_a1 [4] $end
$var wire 1 s loaded_num_a1 [3] $end
$var wire 1 t loaded_num_a1 [2] $end
$var wire 1 u loaded_num_a1 [1] $end
$var wire 1 v loaded_num_a1 [0] $end
$var wire 1 w loaded_num_a2 [7] $end
$var wire 1 x loaded_num_a2 [6] $end
$var wire 1 y loaded_num_a2 [5] $end
$var wire 1 z loaded_num_a2 [4] $end
$var wire 1 { loaded_num_a2 [3] $end
$var wire 1 | loaded_num_a2 [2] $end
$var wire 1 } loaded_num_a2 [1] $end
$var wire 1 ~ loaded_num_a2 [0] $end
$var wire 1 !! loaded_num_a3 [7] $end
$var wire 1 "! loaded_num_a3 [6] $end
$var wire 1 #! loaded_num_a3 [5] $end
$var wire 1 $! loaded_num_a3 [4] $end
$var wire 1 %! loaded_num_a3 [3] $end
$var wire 1 &! loaded_num_a3 [2] $end
$var wire 1 '! loaded_num_a3 [1] $end
$var wire 1 (! loaded_num_a3 [0] $end
$var wire 1 )! loaded_num_b0 [7] $end
$var wire 1 *! loaded_num_b0 [6] $end
$var wire 1 +! loaded_num_b0 [5] $end
$var wire 1 ,! loaded_num_b0 [4] $end
$var wire 1 -! loaded_num_b0 [3] $end
$var wire 1 .! loaded_num_b0 [2] $end
$var wire 1 /! loaded_num_b0 [1] $end
$var wire 1 0! loaded_num_b0 [0] $end
$var wire 1 1! loaded_num_b1 [7] $end
$var wire 1 2! loaded_num_b1 [6] $end
$var wire 1 3! loaded_num_b1 [5] $end
$var wire 1 4! loaded_num_b1 [4] $end
$var wire 1 5! loaded_num_b1 [3] $end
$var wire 1 6! loaded_num_b1 [2] $end
$var wire 1 7! loaded_num_b1 [1] $end
$var wire 1 8! loaded_num_b1 [0] $end
$var wire 1 9! loaded_num_b2 [7] $end
$var wire 1 :! loaded_num_b2 [6] $end
$var wire 1 ;! loaded_num_b2 [5] $end
$var wire 1 <! loaded_num_b2 [4] $end
$var wire 1 =! loaded_num_b2 [3] $end
$var wire 1 >! loaded_num_b2 [2] $end
$var wire 1 ?! loaded_num_b2 [1] $end
$var wire 1 @! loaded_num_b2 [0] $end
$var wire 1 A! loaded_num_b3 [7] $end
$var wire 1 B! loaded_num_b3 [6] $end
$var wire 1 C! loaded_num_b3 [5] $end
$var wire 1 D! loaded_num_b3 [4] $end
$var wire 1 E! loaded_num_b3 [3] $end
$var wire 1 F! loaded_num_b3 [2] $end
$var wire 1 G! loaded_num_b3 [1] $end
$var wire 1 H! loaded_num_b3 [0] $end
$var wire 1 I! matrix_multiplication_done $end

$scope module loader $end
$var wire 1 J! clk $end
$var wire 1 K! nums_a [31] $end
$var wire 1 L! nums_a [30] $end
$var wire 1 M! nums_a [29] $end
$var wire 1 N! nums_a [28] $end
$var wire 1 O! nums_a [27] $end
$var wire 1 P! nums_a [26] $end
$var wire 1 Q! nums_a [25] $end
$var wire 1 R! nums_a [24] $end
$var wire 1 S! nums_a [23] $end
$var wire 1 T! nums_a [22] $end
$var wire 1 U! nums_a [21] $end
$var wire 1 V! nums_a [20] $end
$var wire 1 W! nums_a [19] $end
$var wire 1 X! nums_a [18] $end
$var wire 1 Y! nums_a [17] $end
$var wire 1 Z! nums_a [16] $end
$var wire 1 [! nums_a [15] $end
$var wire 1 \! nums_a [14] $end
$var wire 1 ]! nums_a [13] $end
$var wire 1 ^! nums_a [12] $end
$var wire 1 _! nums_a [11] $end
$var wire 1 `! nums_a [10] $end
$var wire 1 a! nums_a [9] $end
$var wire 1 b! nums_a [8] $end
$var wire 1 c! nums_a [7] $end
$var wire 1 d! nums_a [6] $end
$var wire 1 e! nums_a [5] $end
$var wire 1 f! nums_a [4] $end
$var wire 1 g! nums_a [3] $end
$var wire 1 h! nums_a [2] $end
$var wire 1 i! nums_a [1] $end
$var wire 1 j! nums_a [0] $end
$var wire 1 k! nums_b [31] $end
$var wire 1 l! nums_b [30] $end
$var wire 1 m! nums_b [29] $end
$var wire 1 n! nums_b [28] $end
$var wire 1 o! nums_b [27] $end
$var wire 1 p! nums_b [26] $end
$var wire 1 q! nums_b [25] $end
$var wire 1 r! nums_b [24] $end
$var wire 1 s! nums_b [23] $end
$var wire 1 t! nums_b [22] $end
$var wire 1 u! nums_b [21] $end
$var wire 1 v! nums_b [20] $end
$var wire 1 w! nums_b [19] $end
$var wire 1 x! nums_b [18] $end
$var wire 1 y! nums_b [17] $end
$var wire 1 z! nums_b [16] $end
$var wire 1 {! nums_b [15] $end
$var wire 1 |! nums_b [14] $end
$var wire 1 }! nums_b [13] $end
$var wire 1 ~! nums_b [12] $end
$var wire 1 !" nums_b [11] $end
$var wire 1 "" nums_b [10] $end
$var wire 1 #" nums_b [9] $end
$var wire 1 $" nums_b [8] $end
$var wire 1 %" nums_b [7] $end
$var wire 1 &" nums_b [6] $end
$var wire 1 '" nums_b [5] $end
$var wire 1 (" nums_b [4] $end
$var wire 1 )" nums_b [3] $end
$var wire 1 *" nums_b [2] $end
$var wire 1 +" nums_b [1] $end
$var wire 1 ," nums_b [0] $end
$var reg 8 -" loaded_num_a0 [7:0] $end
$var reg 8 ." loaded_num_a1 [7:0] $end
$var reg 8 /" loaded_num_a2 [7:0] $end
$var reg 8 0" loaded_num_a3 [7:0] $end
$var reg 8 1" loaded_num_b0 [7:0] $end
$var reg 8 2" loaded_num_b1 [7:0] $end
$var reg 8 3" loaded_num_b2 [7:0] $end
$var reg 8 4" loaded_num_b3 [7:0] $end
$var wire 1 5" load $end
$upscope $end

$scope module multiplier $end
$var wire 1 6" clk $end
$var wire 1 7" rst $end
$var wire 1 g loaded_num_a0 [7] $end
$var wire 1 h loaded_num_a0 [6] $end
$var wire 1 i loaded_num_a0 [5] $end
$var wire 1 j loaded_num_a0 [4] $end
$var wire 1 k loaded_num_a0 [3] $end
$var wire 1 l loaded_num_a0 [2] $end
$var wire 1 m loaded_num_a0 [1] $end
$var wire 1 n loaded_num_a0 [0] $end
$var wire 1 o loaded_num_a1 [7] $end
$var wire 1 p loaded_num_a1 [6] $end
$var wire 1 q loaded_num_a1 [5] $end
$var wire 1 r loaded_num_a1 [4] $end
$var wire 1 s loaded_num_a1 [3] $end
$var wire 1 t loaded_num_a1 [2] $end
$var wire 1 u loaded_num_a1 [1] $end
$var wire 1 v loaded_num_a1 [0] $end
$var wire 1 w loaded_num_a2 [7] $end
$var wire 1 x loaded_num_a2 [6] $end
$var wire 1 y loaded_num_a2 [5] $end
$var wire 1 z loaded_num_a2 [4] $end
$var wire 1 { loaded_num_a2 [3] $end
$var wire 1 | loaded_num_a2 [2] $end
$var wire 1 } loaded_num_a2 [1] $end
$var wire 1 ~ loaded_num_a2 [0] $end
$var wire 1 !! loaded_num_a3 [7] $end
$var wire 1 "! loaded_num_a3 [6] $end
$var wire 1 #! loaded_num_a3 [5] $end
$var wire 1 $! loaded_num_a3 [4] $end
$var wire 1 %! loaded_num_a3 [3] $end
$var wire 1 &! loaded_num_a3 [2] $end
$var wire 1 '! loaded_num_a3 [1] $end
$var wire 1 (! loaded_num_a3 [0] $end
$var wire 1 )! loaded_num_b0 [7] $end
$var wire 1 *! loaded_num_b0 [6] $end
$var wire 1 +! loaded_num_b0 [5] $end
$var wire 1 ,! loaded_num_b0 [4] $end
$var wire 1 -! loaded_num_b0 [3] $end
$var wire 1 .! loaded_num_b0 [2] $end
$var wire 1 /! loaded_num_b0 [1] $end
$var wire 1 0! loaded_num_b0 [0] $end
$var wire 1 1! loaded_num_b1 [7] $end
$var wire 1 2! loaded_num_b1 [6] $end
$var wire 1 3! loaded_num_b1 [5] $end
$var wire 1 4! loaded_num_b1 [4] $end
$var wire 1 5! loaded_num_b1 [3] $end
$var wire 1 6! loaded_num_b1 [2] $end
$var wire 1 7! loaded_num_b1 [1] $end
$var wire 1 8! loaded_num_b1 [0] $end
$var wire 1 9! loaded_num_b2 [7] $end
$var wire 1 :! loaded_num_b2 [6] $end
$var wire 1 ;! loaded_num_b2 [5] $end
$var wire 1 <! loaded_num_b2 [4] $end
$var wire 1 =! loaded_num_b2 [3] $end
$var wire 1 >! loaded_num_b2 [2] $end
$var wire 1 ?! loaded_num_b2 [1] $end
$var wire 1 @! loaded_num_b2 [0] $end
$var wire 1 A! loaded_num_b3 [7] $end
$var wire 1 B! loaded_num_b3 [6] $end
$var wire 1 C! loaded_num_b3 [5] $end
$var wire 1 D! loaded_num_b3 [4] $end
$var wire 1 E! loaded_num_b3 [3] $end
$var wire 1 F! loaded_num_b3 [2] $end
$var wire 1 G! loaded_num_b3 [1] $end
$var wire 1 H! loaded_num_b3 [0] $end
$var reg 16 8" result1 [15:0] $end
$var reg 16 9" result2 [15:0] $end
$var reg 16 :" result3 [15:0] $end
$var reg 16 ;" result4 [15:0] $end
$var reg 1 <" matrix_multiplication_done $end
$var reg 4 =" i [3:0] $end
$var reg 16 >" intermediate_result_0 [15:0] $end
$var reg 16 ?" intermediate_result_1 [15:0] $end
$var reg 16 @" intermediate_result_2 [15:0] $end
$var reg 16 A" intermediate_result_3 [15:0] $end
$var reg 16 B" intermediate_result_4 [15:0] $end
$var reg 16 C" intermediate_result_5 [15:0] $end
$var reg 16 D" intermediate_result_6 [15:0] $end
$var reg 16 E" intermediate_result_7 [15:0] $end
$var reg 4 F" pipeline_stage [3:0] $end
$upscope $end
$upscope $end
$enddefinitions $end
#0
$dumpvars
0"
0#
1$
b1000000100000010000001000 %
b1000000110000010100001011 &
bx -"
bx ."
bx /"
bx 0"
bx 1"
bx 2"
bx 3"
bx 4"
bx 8"
bx 9"
bx :"
bx ;"
x<"
bx ="
bx >"
bx ?"
bx @"
bx A"
bx B"
bx C"
bx D"
bx E"
bx F"
b1 !
x'
x(
x)
x*
x+
x,
x-
x.
x/
x0
x1
x2
x3
x4
x5
x6
x7
x8
x9
x:
x;
x<
x=
x>
x?
x@
xA
xB
xC
xD
xE
xF
xG
xH
xI
xJ
xK
xL
xM
xN
xO
xP
xQ
xR
xS
xT
xU
xV
xW
xX
xY
xZ
x[
x\
x]
x^
x_
x`
xa
xb
xc
xd
xe
xf
xn
xm
xl
xk
xj
xi
xh
xg
xv
xu
xt
xs
xr
xq
xp
xo
x~
x}
x|
x{
xz
xy
xx
xw
x(!
x'!
x&!
x%!
x$!
x#!
x"!
x!!
x0!
x/!
x.!
x-!
x,!
x+!
x*!
x)!
x8!
x7!
x6!
x5!
x4!
x3!
x2!
x1!
x@!
x?!
x>!
x=!
x<!
x;!
x:!
x9!
xH!
xG!
xF!
xE!
xD!
xC!
xB!
xA!
xI!
07"
06"
15"
1,"
1+"
0*"
1)"
0("
0'"
0&"
0%"
1$"
0#"
1""
0!"
0~!
0}!
0|!
0{!
1z!
1y!
0x!
0w!
0v!
0u!
0t!
0s!
1r!
0q!
0p!
0o!
0n!
0m!
0l!
0k!
0j!
0i!
0h!
1g!
0f!
0e!
0d!
0c!
0b!
0a!
1`!
0_!
0^!
0]!
0\!
0[!
0Z!
1Y!
0X!
0W!
0V!
0U!
0T!
0S!
1R!
0Q!
0P!
0O!
0N!
0M!
0L!
0K!
0J!
$end
#1000
1"
1J!
16"
b1 -"
b10 ."
b100 /"
b1000 0"
b1 1"
b11 2"
b101 3"
b1011 4"
1H!
1G!
0F!
1E!
0D!
0C!
0B!
0A!
1@!
0?!
1>!
0=!
0<!
0;!
0:!
09!
18!
17!
06!
05!
04!
03!
02!
01!
10!
0/!
0.!
0-!
0,!
0+!
0*!
0)!
0(!
0'!
0&!
1%!
0$!
0#!
0"!
0!!
0~
0}
1|
0{
0z
0y
0x
0w
0v
1u
0t
0s
0r
0q
0p
0o
1n
0m
0l
0k
0j
0i
0h
0g
#2000
0"
0J!
06"
#3000
1"
1J!
16"
#4000
0"
0J!
06"
#5000
0$
1"
05"
1J!
16"
#6000
0"
0J!
06"
#7000
1#
1"
17"
1J!
16"
b0 8"
b0 9"
b0 :"
b0 ;"
b0 >"
b0 ?"
b0 @"
b0 A"
b0 B"
b0 C"
b0 D"
b0 E"
b0 F"
0<"
0W
0X
0Y
0Z
0[
0\
0]
0^
0_
0`
0a
0b
0c
0d
0e
0f
0G
0H
0I
0J
0K
0L
0M
0N
0O
0P
0Q
0R
0S
0T
0U
0V
07
08
09
0:
0;
0<
0=
0>
0?
0@
0A
0B
0C
0D
0E
0F
0'
0(
0)
0*
0+
0,
0-
0.
0/
00
01
02
03
04
05
06
0I!
#8000
0"
0J!
06"
#9000
0#
1"
07"
1J!
16"
b1 >"
b1010 ?"
b1 F"
#10000
0"
0J!
06"
#11000
1"
1J!
16"
b11 @"
b10110 A"
b10 F"
#12000
0"
0J!
06"
#13000
1"
1J!
16"
b100 B"
b101000 C"
b11 F"
#14000
0"
0J!
06"
#15000
1"
1J!
16"
b1100 D"
b1011000 E"
b100 F"
#16000
0"
0J!
06"
#17000
1"
1J!
16"
b1011 8"
b11001 9"
b101100 :"
b1100100 ;"
b101 F"
1Y
1\
1]
1I
1J
1L
17
1:
1;
1'
1(
1*
