james_files/RTL/mult_and_loader_v4_dc_shell/matrix.sv
`timescale 1 ns / 1 ps

module matrix(
    input CLK,
    input [63:0] flat_matrix_1,
    input [63:0] flat_matrix_2,
    input [3:0] R1,
    input [3:0] C1,
    input [3:0] R2,
    input [3:0] C2,
    input readybit,
    output reg [63:0] res_mat
);

    parameter X_DIM = 2;
    parameter Y_DIM = 2;

    reg [127:0] matrix_1 [0:Y_DIM][0:X_DIM];
    reg [127:0] matrix_2 [0:Y_DIM][0:X_DIM];
    reg [127:0] rslt [0:Y_DIM][0:X_DIM];

    reg [31:0] x, y, z, i, j, k, index;
    reg delay;

    always @(posedge CLK) begin

        if(readybit) begin
            #2
            //$display("started: ", $realtime, " ", readybit);

            matrix_1[0][0] = flat_matrix_1[63:48];
            matrix_1[0][1] = flat_matrix_1[47:32];
            matrix_1[1][0] = flat_matrix_1[31:16];
            matrix_1[1][1] = flat_matrix_1[15:0];

            matrix_2[0][0] = flat_matrix_2[63:48];
            matrix_2[0][1] = flat_matrix_2[47:32];
            matrix_2[1][0] = flat_matrix_2[31:16];
            matrix_2[1][1] = flat_matrix_2[15:0];

            // $display("matrix unflattened");
            // $display(matrix_1[0][0], matrix_1[0][1]);
            // $display(matrix_1[1][0], matrix_1[1][1]);
            // $display("matrix unflattened");
            // $display(matrix_2[0][0], matrix_2[0][1]);
            // $display(matrix_2[1][0], matrix_2[1][1]);

            // $display(" ---- Result ----");

            for (i = 0; i < X_DIM; i = i + 1) begin
                for (j = 0; j < Y_DIM; j = j + 1) begin
                    rslt[i][j] = 0;
        
                    for (k = 0; k < X_DIM; k = k + 1) begin
                        rslt[i][j] = rslt[i][j] + matrix_1[i][k] * matrix_2[k][j];
                    end
                  //  $write(rslt[i][j]);
                end
                //$write("\n");
            end

            res_mat[63:48] = rslt[0][0];
            res_mat[47:32] = rslt[0][1];
            res_mat[31:16] = rslt[1][0];
            res_mat[15:0] = rslt[1][1];
        end
    end
endmodule

james_files/RTL/mult_and_loader_v7_optimise/DflopX4.sv
`timescale 1 ns / 1 ps

module DflopX4(
    input wire CLK,
    input wire [7:0] a,
    output reg [7:0] x
    );

    always @(posedge CLK) begin
        x <= a;
    end

endmodule

james_files/RTL/mult_and_loader_v4_dc_shell/data_loader.sv
`timescale 1 ns / 1 ps

module data_loader(
    input wire CLK,
    input wire [7:0] data,
    input wire [1:0] ctrl_logic,
    output reg [63:0] res_mat
);

    parameter Y_DIM = 2;
    parameter X_DIM = 2;

    reg [63:0] matrix_1;
    reg [63:0] matrix_2;

    reg [3:0] R1;
    reg [3:0] C1;

    reg [3:0] R2;
    reg [3:0] C2;

    reg [7:0] data_out;

    reg testFlop;
    reg readybit;

    reg skip;


    DflopX4 data_flop(CLK, data, data_out);
    matrix mult(CLK, matrix_1, matrix_2, R1, C1, R2, C2, readybit, res_mat);

    integer count, testclock;

    integer xS, x, yS, y;


    initial begin
        count <= 0;
        xS = 63;
        x = 0;
        yS = 63;
        y = 0;
        readybit <= 0;
        testclock = -1;

        skip = 1;
    end

    always @(posedge CLK) begin
       // if(skip != 1) begin
    //$display("data: ", data_out, " logic: ", ctrl_logic);

    // size of matrix
        if (ctrl_logic == 1) begin
            //$display("count: ",count, " data: ", data_out);
            case(count)
                3'h1: R1 <= data_out;
                3'h2: C1 <= data_out;
                3'h3: R2 <= data_out;
                3'h4: C2 <= data_out;
            endcase
            count <= count + 1;;
        end else if(ctrl_logic == 0) begin // matrix data
            if(x < C1*R1) begin
                case(x)
                    8'd0:
                        matrix_1[63:48] = data_out;
                    8'd1:
                        matrix_1[47:32] = data_out;
                    8'd2:
                        matrix_1[31:16] = data_out;
                    8'd3:
                        matrix_1[15:0] = data_out;
                endcase
                x = x + 1;
            end else if (y < C2*R2) begin 

                case(y)
                    8'd0:
                        matrix_2[63:48] = data_out;
                    8'd1:
                        matrix_2[47:32] = data_out;
                    8'd2:
                        matrix_2[31:16] = data_out;
                    8'd3:
                        matrix_2[15:0] = data_out;
                endcase
                y = y + 1;  
            end

            //$display("ckock: ", testclock, " t/f: ", (x==R1*C1) && (y==R2*C2), " logic: ", ctrl_logic, " xy: ", x,y);
            if ((x==R1*C1) && (y==R2*C2))
                //$display("mult now");
                readybit <= 1;
        end else if (ctrl_logic == 2) begin
            
            //$display("here");
            readybit <= 0;
            x = 0;
            y = 0;
            count <= 0;
        end
        skip = 0;
    end

endmodule

james_files/RTL/mult_and_loader_v4_dc_shell/advanced_tb.sv
`timescale 1 ns / 1 ps

module advanced_tb();

    parameter NUM_MAT = 3; // set num of matrix to mult
    parameter MAT_SIZE = 4; // set num of matrix to mult
    parameter MAT_XxX = 2; // x by x size

    reg CLK;
    reg [1:0] ctrl_logic;
    reg [7:0] data_send;
    
    reg [7:0] load_data [0:127];
    reg [1:0] load_logic [0:255];

    reg [63:0] res_mat;

    wire S0;

    integer data_i, logic_i, count; // matrix indexes
    integer i, j, k;                // for loop ints

    reg testo;

    data_loader loader(CLK, data_send, ctrl_logic, res_mat);

    initial begin
        

        $dumpfile("waveform.vcd"); // Specifies the name of the dump file
        $dumpvars(0, advanced_tb);   // Dumps all variables in the module "testbench" and its submodules
        CLK = 0;
        count = 1;
        logic_i = 0;
        data_i  = 0;

        ctrl_logic = 1;
        data_send = 2;

        // load data for NUM_MAT of MAT_SIZE * 2, (*2 for 2 matrix per mult)
        for(i = 0; i < NUM_MAT * MAT_SIZE * 2; i++ ) begin
            load_data[i] = $random;
        end

        // load ctrl logic,
        for(i = 0; i < NUM_MAT*14; i++ ) begin

            if(i != 0) begin
                load_logic[i] = 2;
                i = i + 1;
            end
                
            for(j = 0; j < 4; j++) begin
                load_logic[i] = 1;
                i = i + 1;
            end
            for(j = 0; j < 2*MAT_SIZE; j++) begin
                load_logic[i] = 0;
                i = i + 1;
            end
            load_logic[i] = 2;
        end

        // for(i = 0; i < NUM_MAT*8; i++)
        //     $display(load_data[i]);
        // $display("---------------------------------------------------------");
        //  for(i = 0; i < NUM_MAT*14; i++)
        //      $display(load_logic[i]);

        forever #0.5 CLK = ~CLK;
    end

    //always #5 CLK=~CLK; //clock toggle every 0.5 ns

    always @(posedge CLK) begin

        ctrl_logic <= load_logic[logic_i++];
        case(count)
            8'h0:
                data_send <= MAT_XxX;
            8'h1:
                data_send <= MAT_XxX;
            8'h2:
                data_send <= MAT_XxX;
            8'h3: 
                data_send <= MAT_XxX;
            8'h4: begin
                data_send <= load_data[data_i];
                data_i = data_i + 1;
            end
            8'h5: begin
                data_send <= load_data[data_i];
                data_i = data_i + 1;
            end
            8'h6: begin
                data_send <= load_data[data_i];
                data_i = data_i + 1;
            end
            8'h7: begin
                data_send <= load_data[data_i];
                data_i = data_i + 1;
            end
            8'h8: begin
                data_send <= load_data[data_i];
                data_i = data_i + 1;
            end
            8'h9: begin
                data_send <= load_data[data_i];
                data_i = data_i + 1;
            end
            8'hA: begin
                data_send <= load_data[data_i];
                data_i = data_i + 1;
            end
            8'hB: begin
                data_send <= load_data[data_i];
                data_i = data_i + 1;
            end
            8'hC:
                data_send <= 0;
            8'hD:
                data_send <= 0;
        endcase
        
        // || (logic_i == 14 & count == 14)
        if(count == 13) begin
            count = 0;
            #5

            // rslt_tb[0][0] = loader.mult.rslt[0][0];
            // rslt_tb[0][1] = loader.mult.rslt[0][1];
            // rslt_tb[1][0] = loader.mult.rslt[1][0];
            // rslt_tb[1][1] = loader.mult.rslt[1][1];
            
            // $display("--- result ---");
            // $display(rslt_tb[0][0]," ", rslt_tb[0][1]);
            // $display(rslt_tb[1][0]," ", rslt_tb[1][1]);

            $display("--- result ---");
            $display(res_mat[63:48]," ", res_mat[47:32]);
            $display(res_mat[31:16]," ", res_mat[15:0]);
        end else begin
            count = count + 1;
        end

        if(logic_i == 14*NUM_MAT) begin
            #10
            $finish;
        end 
    end
endmodule

james_files/RTL/mult_and_loader_v4_dc_shell/waveform.vcd
$date
	Fri Apr 19 22:13:23 2024
$end
$version
	Icarus Verilog
$end
$timescale
	1ps
$end
$scope module advanced_tb $end
$var wire 64 ! res_mat [63:0] $end
$var parameter 32 " MAT_SIZE $end
$var parameter 32 # MAT_XxX $end
$var parameter 32 $ NUM_MAT $end
$var reg 1 % CLK $end
$var reg 2 & ctrl_logic [1:0] $end
$var reg 8 ' data_send [7:0] $end
$var integer 32 ( count [31:0] $end
$var integer 32 ) data_i [31:0] $end
$var integer 32 * i [31:0] $end
$var integer 32 + j [31:0] $end
$var integer 32 , logic_i [31:0] $end
$scope module loader $end
$var wire 1 % CLK $end
$var wire 2 - ctrl_logic [1:0] $end
$var wire 8 . data [7:0] $end
$var wire 64 / res_mat [63:0] $end
$var wire 8 0 data_out [7:0] $end
$var parameter 32 1 X_DIM $end
$var parameter 32 2 Y_DIM $end
$var reg 4 3 C1 [3:0] $end
$var reg 4 4 C2 [3:0] $end
$var reg 4 5 R1 [3:0] $end
$var reg 4 6 R2 [3:0] $end
$var reg 64 7 matrix_1 [63:0] $end
$var reg 64 8 matrix_2 [63:0] $end
$var reg 1 9 readybit $end
$var reg 1 : skip $end
$var integer 32 ; count [31:0] $end
$var integer 32 < testclock [31:0] $end
$var integer 32 = x [31:0] $end
$var integer 32 > xS [31:0] $end
$var integer 32 ? y [31:0] $end
$var integer 32 @ yS [31:0] $end
$scope module data_flop $end
$var wire 1 % CLK $end
$var wire 8 A a [7:0] $end
$var reg 8 B x [7:0] $end
$upscope $end
$scope module mult $end
$var wire 4 C C1 [3:0] $end
$var wire 4 D C2 [3:0] $end
$var wire 1 % CLK $end
$var wire 4 E R1 [3:0] $end
$var wire 4 F R2 [3:0] $end
$var wire 64 G flat_matrix_1 [63:0] $end
$var wire 64 H flat_matrix_2 [63:0] $end
$var wire 1 9 readybit $end
$var parameter 32 I X_DIM $end
$var parameter 32 J Y_DIM $end
$var reg 32 K i [31:0] $end
$var reg 32 L j [31:0] $end
$var reg 32 M k [31:0] $end
$var reg 64 N res_mat [63:0] $end
$upscope $end
$upscope $end
$upscope $end
$enddefinitions $end
$comment Show the parameter values. $end
$dumpall
b10 J
b10 I
b10 2
b10 1
b11 $
b10 #
b100 "
$end
#0
$dumpvars
bx N
bx M
bx L
bx K
bx H
bx G
bx F
bx E
bx D
bx C
bx B
b10 A
b111111 @
b0 ?
b111111 >
b0 =
b11111111111111111111111111111111 <
b0 ;
1:
09
bx 8
bx 7
bx 6
bx 5
bx 4
bx 3
bx 0
bx /
b10 .
b1 -
b0 ,
b1000 +
b110111 *
b0 )
b1 (
b10 '
b1 &
0%
bx !
$end
#500
b10 0
b10 B
b1 ;
0:
b10 (
b1 ,
1%
#1000
0%
#1500
b10 ;
b10 5
b10 E
b11 (
b10 ,
1%
#2000
0%
#2500
b11 ;
b10 3
b10 C
b100 (
b11 ,
1%
#3000
0%
#3500
b100100 '
b100100 .
b100100 A
b100 ;
b10 6
b10 F
b101 (
b1 )
b100 ,
1%
#4000
0%
#4500
b100100 0
b100100 B
b101 ;
b10 4
b10 D
b10000001 '
b10000001 .
b10000001 A
b0 &
b0 -
b110 (
b10 )
b101 ,
1%
#5000
0%
#5500
b1001 '
b1001 .
b1001 A
b10000001 0
b10000001 B
b111 (
b11 )
b110 ,
b1 =
b100100xxxxxxxxxxxxxxxxxxxxxxxxxxxxxxxxxxxxxxxxxxxxxxxx 7
b100100xxxxxxxxxxxxxxxxxxxxxxxxxxxxxxxxxxxxxxxxxxxxxxxx G
1%
#6000
0%
#6500
b1001 0
b1001 B
b1100011 '
b1100011 .
b1100011 A
b10 =
b1001000000000010000001xxxxxxxxxxxxxxxxxxxxxxxxxxxxxxxx 7
b1001000000000010000001xxxxxxxxxxxxxxxxxxxxxxxxxxxxxxxx G
b1000 (
b100 )
b111 ,
1%
#7000
0%
#7500
b1101 '
b1101 .
b1101 A
b1100011 0
b1100011 B
b1001 (
b101 )
b1000 ,
b11 =
b10010000000000100000010000000000001001xxxxxxxxxxxxxxxx 7
b10010000000000100000010000000000001001xxxxxxxxxxxxxxxx G
1%
#8000
0%
#8500
b1101 0
b1101 B
b10001101 '
b10001101 .
b10001101 A
b100 =
b100100000000001000000100000000000010010000000001100011 7
b100100000000001000000100000000000010010000000001100011 G
b1010 (
b110 )
b1001 ,
1%
#9000
0%
#9500
b1100101 '
b1100101 .
b1100101 A
b10001101 0
b10001101 B
b1011 (
b111 )
b1010 ,
b1 ?
b1101xxxxxxxxxxxxxxxxxxxxxxxxxxxxxxxxxxxxxxxxxxxxxxxx 8
b1101xxxxxxxxxxxxxxxxxxxxxxxxxxxxxxxxxxxxxxxxxxxxxxxx H
1%
#10000
0%
#10500
b1100101 0
b1100101 B
b10010 '
b10010 .
b10010 A
b10 ?
b11010000000010001101xxxxxxxxxxxxxxxxxxxxxxxxxxxxxxxx 8
b11010000000010001101xxxxxxxxxxxxxxxxxxxxxxxxxxxxxxxx H
b1100 (
b1000 )
b1011 ,
1%
#11000
0%
#11500
b0 '
b0 .
b0 A
b10010 0
b10010 B
b1101 (
b1100 ,
b11 ?
b110100000000100011010000000001100101xxxxxxxxxxxxxxxx 8
b110100000000100011010000000001100101xxxxxxxxxxxxxxxx H
1%
#12000
0%
#12500
b0 0
b0 B
19
b10 &
b10 -
b100 ?
b1101000000001000110100000000011001010000000000010010 8
b1101000000001000110100000000011001010000000000010010 H
b0 (
b1101 ,
1%
#13000
0%
#13500
b0 ;
09
b0 ?
b0 =
1%
#14000
0%
#14500
1%
#15000
0%
#15500
1%
b11010010111001000111001110011000100111100001000000101111101011 !
b11010010111001000111001110011000100111100001000000101111101011 /
b11010010111001000111001110011000100111100001000000101111101011 N
b10 M
b10 L
b10 K
#16000
0%
#16500
1%
#17000
0%
#17500
b10 '
b10 .
b10 A
b1 (
b1110 ,
1%
#18000
0%
#18500
b1 &
b1 -
b10 0
b10 B
b10 (
b1111 ,
1%
#19000
0%
#19500
b1 ;
b11 (
b10000 ,
1%
#20000
0%
#20500
b10 ;
b100 (
b10001 ,
1%
#21000
0%
#21500
b11 ;
b1 '
b1 .
b1 A
b101 (
b1001 )
b10010 ,
1%
#22000
0%
#22500
b1101 '
b1101 .
b1101 A
b0 &
b0 -
b1 0
b1 B
b100 ;
b110 (
b1010 )
b10011 ,
1%
#23000
0%
#23500
b1101 0
b1101 B
b1110110 '
b1110110 .
b1110110 A
b1 =
b1000000001000000100000000000010010000000001100011 7
b1000000001000000100000000000010010000000001100011 G
b111 (
b1011 )
b10100 ,
1%
#24000
0%
#24500
b111101 '
b111101 .
b111101 A
b1110110 0
b1110110 B
b1000 (
b1100 )
b10101 ,
b10 =
b1000000000000110100000000000010010000000001100011 7
b1000000000000110100000000000010010000000001100011 G
1%
#25000
0%
#25500
b111101 0
b111101 B
b11101101 '
b11101101 .
b11101101 A
b11 =
b1000000000000110100000000011101100000000001100011 7
b1000000000000110100000000011101100000000001100011 G
b1001 (
b1101 )
b10110 ,
1%
#26000
0%
#26500
b10001100 '
b10001100 .
b10001100 A
b11101101 0
b11101101 B
b1010 (
b1110 )
b10111 ,
b100 =
b1000000000000110100000000011101100000000000111101 7
b1000000000000110100000000011101100000000000111101 G
1%
#27000
0%
#27500
b10001100 0
b10001100 B
b11111001 '
b11111001 .
b11111001 A
b1 ?
b11101101000000001000110100000000011001010000000000010010 8
b11101101000000001000110100000000011001010000000000010010 H
b1011 (
b1111 )
b11000 ,
1%
#28000
0%
#28500
b11000110 '
b11000110 .
b11000110 A
b11111001 0
b11111001 B
b1100 (
b10000 )
b11001 ,
b10 ?
b11101101000000001000110000000000011001010000000000010010 8
b11101101000000001000110000000000011001010000000000010010 H
1%
#29000
0%
#29500
b11000110 0
b11000110 B
b0 '
b0 .
b0 A
b11 ?
b11101101000000001000110000000000111110010000000000010010 8
b11101101000000001000110000000000111110010000000000010010 H
b1101 (
b11010 ,
1%
#30000
0%
#30500
b10 &
b10 -
b0 0
b0 B
19
b0 (
b11011 ,
b100 ?
b11101101000000001000110000000000111110010000000011000110 8
b11101101000000001000110000000000111110010000000011000110 H
1%
#31000
0%
#31500
b0 ;
09
b0 ?
b0 =
1%
#32000
0%
#32500
1%
#33000
0%
#33500
1%
b110110010010000010101001101010101000100100110110111110110110 !
b110110010010000010101001101010101000100100110110111110110110 /
b110110010010000010101001101010101000100100110110111110110110 N
b10 M
b10 L
b10 K
#34000
0%
#34500
1%
#35000
0%
#35500
b10 '
b10 .
b10 A
b1 (
b11100 ,
1%
#36000
0%
#36500
b1 &
b1 -
b10 0
b10 B
b10 (
b11101 ,
1%
#37000
0%
#37500
b1 ;
b11 (
b11110 ,
1%
#38000
0%
#38500
b10 ;
b100 (
b11111 ,
1%
#39000
0%
#39500
b11 ;
b11000101 '
b11000101 .
b11000101 A
b101 (
b10001 )
b100000 ,
1%
#40000
0%
#40500
b10101010 '
b10101010 .
b10101010 A
b0 &
b0 -
b11000101 0
b11000101 B
b100 ;
b110 (
b10010 )
b100001 ,
1%
#41000
0%
#41500
b10101010 0
b10101010 B
b11100101 '
b11100101 .
b11100101 A
b1 =
b11000101000000000000110100000000011101100000000000111101 7
b11000101000000000000110100000000011101100000000000111101 G
b111 (
b10011 )
b100010 ,
1%
#42000
0%
#42500
b1110111 '
b1110111 .
b1110111 A
b11100101 0
b11100101 B
b1000 (
b10100 )
b100011 ,
b10 =
b11000101000000001010101000000000011101100000000000111101 7
b11000101000000001010101000000000011101100000000000111101 G
1%
#43000
0%
#43500
b1110111 0
b1110111 B
b10010 '
b10010 .
b10010 A
b11 =
b11000101000000001010101000000000111001010000000000111101 7
b11000101000000001010101000000000111001010000000000111101 G
b1001 (
b10101 )
b100100 ,
1%
#44000
0%
#44500
b10001111 '
b10001111 .
b10001111 A
b10010 0
b10010 B
b1010 (
b10110 )
b100101 ,
b100 =
b11000101000000001010101000000000111001010000000001110111 7
b11000101000000001010101000000000111001010000000001110111 G
1%
#45000
0%
#45500
b10001111 0
b10001111 B
b11110010 '
b11110010 .
b11110010 A
b1 ?
b10010000000001000110000000000111110010000000011000110 8
b10010000000001000110000000000111110010000000011000110 H
b1011 (
b10111 )
b100110 ,
1%
#46000
0%
#46500
b11001110 '
b11001110 .
b11001110 A
b11110010 0
b11110010 B
b1100 (
b11000 )
b100111 ,
b10 ?
b10010000000001000111100000000111110010000000011000110 8
b10010000000001000111100000000111110010000000011000110 H
1%
#47000
0%
#47500
b11001110 0
b11001110 B
b0 '
b0 .
b0 A
b11 ?
b10010000000001000111100000000111100100000000011000110 8
b10010000000001000111100000000111100100000000011000110 H
b1101 (
b101000 ,
1%
#48000
0%
#48500
b10 &
b10 -
b0 0
b0 B
19
b0 (
b101001 ,
b100 ?
b10010000000001000111100000000111100100000000011001110 8
b10010000000001000111100000000111100100000000011001110 H
1%
#49000
0%
#49500
b0 ;
09
b0 ?
b0 =
1%
#50000
0%
#50500
1%
#51000
0%
#51500
1%
b1010111010001110111101101101011110000000100110001101111110101101 !
b1010111010001110111101101101011110000000100110001101111110101101 /
b1010111010001110111101101101011110000000100110001101111110101101 N
b10 M
b10 L
b10 K
#52000
0%
#52500
1%
#53000
0%
#53500
b10 '
b10 .
b10 A
b1 (
b101010 ,
1%
#54000
0%
#54500
b10 0
b10 B
1%
